{"type":"Topology","objects":{"data":{"geometries":[{"properties":{"id":"CI-1203","name":"WORODOUGOU","biome":null,"country":"COTE D'IVOIRE","trase_id":"CI-1203","parent_name":"WOROBA","node_type_name":"Region","node_type_slug":"region","parent_node_type_name":"District"},"type":"MultiPolygon","arcs":[[[-26,0,-24,1,-22,2,-573,3,-571,4,-179,5,-40,6,-51,7,-49,8,-60,9,-58,10,-56,11,-81,12,-28,13]]],"id":0},{"properties":{"id":"CI-1202","name":"BERE","biome":null,"country":"COTE D'IVOIRE","trase_id":"CI-1202","parent_name":"WOROBA","node_type_name":"Region","node_type_slug":"region","parent_node_type_name":"District"},"type":"MultiPolygon","arcs":[[[-286,14,-284,15,-282,16,-280,17,-548,18,-546,19,-575,20,21,22,23,24,25,26,27,28,-79,-110,29,-108,30,-230,31,-269,32,-267,33,-265,34,-263,35,-290,36,-288,37]]],"id":1},{"properties":{"id":"CI-1201","name":"BAFING","biome":null,"country":"COTE D'IVOIRE","trase_id":"CI-1201","parent_name":"WOROBA","node_type_name":"Region","node_type_slug":"region","parent_node_type_name":"District"},"type":"MultiPolygon","arcs":[[[38,39,40,-177,41,-175,42,-173,43,-171,44,-66,45,-64,46,-62,47,48,49,50]]],"id":2},{"properties":{"id":"CI-0402","name":"KABADOUGOU","biome":null,"country":"COTE D'IVOIRE","trase_id":"CI-0402","parent_name":"DENGUELE","node_type_name":"Region","node_type_slug":"region","parent_node_type_name":"District"},"type":"MultiPolygon","arcs":[[[-74,-73,51,-71,52,-69,53,-83,54,55,56,57,58,59,60,61,62,63,64,65,66,-75]]],"id":3},{"properties":{"id":"CI-0401","name":"FOLON","biome":null,"country":"COTE D'IVOIRE","trase_id":"CI-0401","parent_name":"DENGUELE","node_type_name":"Region","node_type_slug":"region","parent_node_type_name":"District"},"type":"MultiPolygon","arcs":[[[-85,67,68,69,70,71,72,73,74,75]]],"id":4},{"properties":{"id":"CI-1001","name":"BAGOUE","biome":null,"country":"COTE D'IVOIRE","trase_id":"CI-1001","parent_name":"SAVANES","node_type_name":"Region","node_type_slug":"region","parent_node_type_name":"District"},"type":"MultiPolygon","arcs":[[[76,-113,77,-111,78,79,80,81,82,83,84,85,-119,86,-117,87,-115]]],"id":5},{"properties":{"id":"CI-1003","name":"TCHOLOGO","biome":null,"country":"COTE D'IVOIRE","trase_id":"CI-1003","parent_name":"SAVANES","node_type_name":"Region","node_type_slug":"region","parent_node_type_name":"District"},"type":"MultiPolygon","arcs":[[[-147,88,-145,89,-143,90,-141,91,-139,92,-137,93,-135,94,-252,95,-250,96,-248,97,-246,98,-244,99,-242,100,-127,101,-125,102,-123,103,-121,104]]],"id":6},{"properties":{"id":"CI-1002","name":"PORO","biome":null,"country":"COTE D'IVOIRE","trase_id":"CI-1002","parent_name":"SAVANES","node_type_name":"Region","node_type_slug":"region","parent_node_type_name":"District"},"type":"MultiPolygon","arcs":[[[-234,105,-232,106,107,108,109,110,111,112,113,114,115,116,117,118,119,120,121,122,123,124,125,126,127,-240,128,-238,129,-236,130]]],"id":7},{"properties":{"id":"CI-1401","name":"BOUNKANI","biome":null,"country":"COTE D'IVOIRE","trase_id":"CI-1401","parent_name":"ZANZAN","node_type_name":"Region","node_type_slug":"region","parent_node_type_name":"District"},"type":"MultiPolygon","arcs":[[[-161,131,-256,132,-254,133,134,135,136,137,138,139,140,141,142,143,144,145,146,147,-163,148]]],"id":8},{"properties":{"id":"CI-1402","name":"GONTOUGO","biome":null,"country":"COTE D'IVOIRE","trase_id":"CI-1402","parent_name":"ZANZAN","node_type_name":"Region","node_type_slug":"region","parent_node_type_name":"District"},"type":"MultiPolygon","arcs":[[[-540,149,-538,150,-536,151,-534,152,-325,153,-353,154,-351,155,-349,156,-347,157,-345,-260,158,-258,159,160,161,162,163]]],"id":9},{"properties":{"id":"CI-0803","name":"TONKPI","biome":null,"country":"COTE D'IVOIRE","trase_id":"CI-0803","parent_name":"MONTAGNES","node_type_name":"Region","node_type_slug":"region","parent_node_type_name":"District"},"type":"MultiPolygon","arcs":[[[-205,164,-203,165,-201,166,-199,167,-197,168,-195,169,170,171,172,173,174,175,176,177,178,179,-189,180,-187,181,-207,182]]],"id":10},{"properties":{"id":"CI-0802","name":"GUEMON","biome":null,"country":"COTE D'IVOIRE","trase_id":"CI-0802","parent_name":"MONTAGNES","node_type_name":"Region","node_type_slug":"region","parent_node_type_name":"District"},"type":"MultiPolygon","arcs":[[[-563,183,-503,184,-209,185,186,187,188,189,-569,190,-567,191,-565,192]]],"id":11},{"properties":{"id":"CI-0801","name":"CAVALLY","biome":null,"country":"COTE D'IVOIRE","trase_id":"CI-0801","parent_name":"MONTAGNES","node_type_name":"Region","node_type_slug":"region","parent_node_type_name":"District"},"type":"MultiPolygon","arcs":[[[-501,-468,193,194,195,196,197,198,199,200,201,202,203,204,205,206,207,208,209]]],"id":12},{"properties":{"id":"CI-0501","name":"GOH","biome":null,"country":"COTE D'IVOIRE","trase_id":"CI-0501","parent_name":"GOH-DJIBOUA","node_type_name":"Region","node_type_slug":"region","parent_node_type_name":"District"},"type":"MultiPolygon","arcs":[[[210,-470,211,-507,212,-557,213,-543,214,-596,215,-356,216,-412,217,-225]]],"id":13},{"properties":{"id":"CI-0502","name":"LOH-DJIBOUA","biome":null,"country":"COTE D'IVOIRE","trase_id":"CI-0502","parent_name":"GOH-DJIBOUA","node_type_name":"Region","node_type_slug":"region","parent_node_type_name":"District"},"type":"MultiPolygon","arcs":[[[-432,218,-444,219,-442,220,-440,221,-474,222,-472,223,224,225,-410,226,-408,227]]],"id":14},{"properties":{"id":"CI-1102","name":"HAMBOL","biome":null,"country":"COTE D'IVOIRE","trase_id":"CI-1102","parent_name":"VALLEE DU BANDAMA","node_type_name":"Region","node_type_slug":"region","parent_node_type_name":"District"},"type":"MultiPolygon","arcs":[[[228,229,230,231,232,233,234,235,236,237,238,239,240,241,242,243,244,245,246,247,248,249,250,251,252,253,254,255,256,257,258,259,-344,260,-292,261,262,263,264,265,266,267,268]]],"id":15},{"properties":{"id":"CI-1101","name":"GBEKE","biome":null,"country":"COTE D'IVOIRE","trase_id":"CI-1101","parent_name":"VALLEE DU BANDAMA","node_type_name":"Region","node_type_slug":"region","parent_node_type_name":"District"},"type":"MultiPolygon","arcs":[[[269,-342,270,-340,271,-377,272,-375,273,-395,274,-393,275,-391,276,-389,277,-550,278,279,280,281,282,283,284,285,286,287,288,289,290,291]]],"id":16},{"properties":{"id":"CI-0604","name":"N'ZI","biome":null,"country":"COTE D'IVOIRE","trase_id":"CI-0604","parent_name":"LACS","node_type_name":"Region","node_type_slug":"region","parent_node_type_name":"District"},"type":"MultiPolygon","arcs":[[[-319,292,-363,293,-361,294,-359,295,-592,296,-383,297,-381,298,-337,-306,299,-304,300,-323,301,-321,302]]],"id":17},{"properties":{"id":"CI-0603","name":"MORONOU","biome":null,"country":"COTE D'IVOIRE","trase_id":"CI-0603","parent_name":"LACS","node_type_name":"Region","node_type_slug":"region","parent_node_type_name":"District"},"type":"MultiPolygon","arcs":[[[303,304,305,-336,306,-334,307,-332,308,-522,309,-520,310,-403,311,-420,312,-418,313,-371,314,-369,315,-367,316,-365,317,318,319,320,321,322,323]]],"id":18},{"properties":{"id":"CI-0602","name":"IFFOU","biome":null,"country":"COTE D'IVOIRE","trase_id":"CI-0602","parent_name":"LACS","node_type_name":"Region","node_type_slug":"region","parent_node_type_name":"District"},"type":"MultiPolygon","arcs":[[[324,325,-532,326,-530,327,-528,328,-526,329,-524,330,331,332,333,334,335,336,337,-379,338,339,340,341,342,343,344,345,346,347,348,349,350,351,352,353]]],"id":19},{"properties":{"id":"CI-0601","name":"BELIER","biome":null,"country":"COTE D'IVOIRE","trase_id":"CI-0601","parent_name":"LACS","node_type_name":"Region","node_type_slug":"region","parent_node_type_name":"District"},"type":"MultiPolygon","arcs":[[[-414,354,355,356,-594,357,358,359,360,361,362,363,364,365,366,367,368,369,370,371,-416,372]],[[373,374,375,376,377,378,379,380,381,382,383,-590,384,-588,385,-602,386,-553,387,388,389,390,391,392,393,394]]],"id":20},{"properties":{"id":"CI-0703","name":"ME","biome":null,"country":"COTE D'IVOIRE","trase_id":"CI-0703","parent_name":"LAGUNES","node_type_name":"Region","node_type_slug":"region","parent_node_type_name":"District"},"type":"MultiPolygon","arcs":[[[-516,395,-511,396,-509,-580,397,-428,398,-426,399,-424,400,-422,401,402,403,-518,404]]],"id":21},{"properties":{"id":"CI-0701","name":"AGNEBY-TIASSA","biome":null,"country":"COTE D'IVOIRE","trase_id":"CI-0701","parent_name":"LAGUNES","node_type_name":"Region","node_type_slug":"region","parent_node_type_name":"District"},"type":"MultiPolygon","arcs":[[[-436,405,-434,406,407,408,409,410,411,412,413,414,415,416,417,418,419,420,421,422,423,424,425,426,427,428,-578,429,-586]]],"id":22},{"properties":{"id":"CI-0702","name":"GRAND-PONTS","biome":null,"country":"COTE D'IVOIRE","trase_id":"CI-0702","parent_name":"LAGUNES","node_type_name":"Region","node_type_slug":"region","parent_node_type_name":"District"},"type":"MultiPolygon","arcs":[[[430,431,432,433,434,435,-585,436,-583]]],"id":23},{"properties":{"id":"CI-0201","name":"GBOKLE","biome":null,"country":"COTE D'IVOIRE","trase_id":"CI-0201","parent_name":"BAS-SASSANDRA","node_type_name":"Region","node_type_slug":"region","parent_node_type_name":"District"},"type":"MultiPolygon","arcs":[[[-478,437,-476,438,439,440,441,442,443,444,-466,445,-464,446,-462,447,-460,448,-490,449,-488,450,-486,451,-484,452,-482,453,-480,454]]],"id":24},{"properties":{"id":"CI-0203","name":"SAN-PEDRO","biome":null,"country":"COTE D'IVOIRE","trase_id":"CI-0203","parent_name":"BAS-SASSANDRA","node_type_name":"Region","node_type_slug":"region","parent_node_type_name":"District"},"type":"MultiPolygon","arcs":[[[-498,455,-496,456,-494,457,-492,458,459,460,461,462,463,464,465,466,467,-500,468]]],"id":25},{"properties":{"id":"CI-0202","name":"NAWA","biome":null,"country":"COTE D'IVOIRE","trase_id":"CI-0202","parent_name":"BAS-SASSANDRA","node_type_name":"Region","node_type_slug":"region","parent_node_type_name":"District"},"type":"MultiPolygon","arcs":[[[469,470,471,472,473,474,475,476,477,478,479,480,481,482,483,484,485,486,487,488,489,490,491,492,493,494,495,496,497,498,499,500,501,502,503,-561,504,-559,505,506,507]]],"id":26},{"properties":{"id":"CI-0302","name":"SUD-COMOE","biome":null,"country":"COTE D'IVOIRE","trase_id":"CI-0302","parent_name":"COMOE","node_type_name":"Region","node_type_slug":"region","parent_node_type_name":"District"},"type":"MultiPolygon","arcs":[[[-581,508,509,510,511,-514,512]]],"id":27},{"properties":{"id":"CI-0301","name":"INDENIE-DJUABLIN","biome":null,"country":"COTE D'IVOIRE","trase_id":"CI-0301","parent_name":"COMOE","node_type_name":"Region","node_type_slug":"region","parent_node_type_name":"District"},"type":"MultiPolygon","arcs":[[[513,514,515,516,517,518,519,520,521,522,523,524,525,526,527,528,529,530,531,532,533,534,535,536,537,538,539,540]]],"id":28},{"properties":{"id":"CI-0902","name":"MARAHOUE","biome":null,"country":"COTE D'IVOIRE","trase_id":"CI-0902","parent_name":"SASSANDRA-MARAHOUE","node_type_name":"Region","node_type_slug":"region","parent_node_type_name":"District"},"type":"MultiPolygon","arcs":[[[-598,541,542,543,-577,544,545,546,547,548,549,550,551,552,553,-600,554]]],"id":29},{"properties":{"id":"CI-0901","name":"HAUT-SASSANDRA","biome":null,"country":"COTE D'IVOIRE","trase_id":"CI-0901","parent_name":"SASSANDRA-MARAHOUE","node_type_name":"Region","node_type_slug":"region","parent_node_type_name":"District"},"type":"MultiPolygon","arcs":[[[555,556,557,558,559,560,561,562,563,564,565,566,567,568,569,570,571,572,573,574,575,576]]],"id":30},{"properties":{"id":"CI-0101","name":"AUTONOME D'ABIDJAN","biome":null,"country":"COTE D'IVOIRE","trase_id":"CI-0101","parent_name":"ABIDJAN","node_type_name":"Region","node_type_slug":"region","parent_node_type_name":"District"},"type":"MultiPolygon","arcs":[[[577,578,579,580,581,582,583,584,585,586]]],"id":31},{"properties":{"id":"CI-1301","name":"AUTONOME DE YAMOUSSOUKRO","biome":null,"country":"COTE D'IVOIRE","trase_id":"CI-1301","parent_name":"YAMOUSSOUKRO","node_type_name":"Region","node_type_slug":"region","parent_node_type_name":"District"},"type":"MultiPolygon","arcs":[[[587,588,589,590,591,592,593,594,595,596,597,598,599,600,601,602]]],"id":32}],"type":"GeometryCollection"}},"bbox":[-8.6018,4.3605,-2.4941,10.7456],"transform":{"scale":[6.107761077610778e-05,6.385163851638516e-05],"translate":[-8.6018,4.3605]},"arcs":[[[36830,61500],[82,-308],[-47,-155],[60,-335]],[[37542,58880],[208,-1433],[194,-377]],[[38310,53593],[162,-38]],[[31863,53876],[-5927,21],[-658,-1731]],[[25037,52105],[64,373],[-128,193],[-49,1279],[75,735]],[[25153,55925],[62,224],[-121,420],[153,357],[-501,319],[-36,219],[117,170]],[[24290,62225],[-497,199],[0,245]],[[23426,64031],[-72,176],[218,152]],[[23545,64731],[-131,50],[-278,347],[146,150]],[[22737,66387],[232,56],[-60,376]],[[22517,71566],[110,338],[675,-62]],[[28909,73594],[396,258],[677,290],[399,78]],[[30820,74324],[319,-161],[-64,-296],[36,-331]],[[35784,63965],[38,-294],[13,-121],[145,69]],[[47140,55154],[-467,127],[-209,-169],[-90,-260]],[[46429,54526],[-81,-368],[170,-333],[268,-196],[238,-64]],[[48219,51065],[-21,-191],[-618,-296]],[[47919,50091],[-353,-308],[-295,-179],[-329,285]],[[45994,52949],[-213,176],[-322,19]],[[41426,51451],[-108,42],[-26,-72],[-503,26],[-33,-90]],[[38587,53488],[-277,105]],[[38310,53593],[-34,75],[121,138],[-23,288],[98,213],[-91,224],[75,324],[-33,245],[138,249],[-169,330],[-13,293],[31,218],[185,241],[53,225],[-392,340],[-23,111],[-289,-37]],[[37944,57070],[-184,351],[-218,1459]],[[37542,58880],[45,121],[-228,976],[-257,588],[-177,137]],[[36925,60702],[-95,798]],[[36830,61500],[97,50],[-82,699],[87,254],[-185,94],[250,195],[-381,66],[177,124],[-195,424],[-164,30],[-146,146],[-308,37]],[[35980,63619],[-158,-65],[-38,411]],[[35784,63965],[-260,109],[50,410],[-124,92],[-296,16],[-118,200],[77,212],[101,64],[215,-207],[49,144],[111,10],[74,208],[-148,204],[-72,437],[-96,48],[-72,-94],[-134,147],[275,135],[-138,155],[218,88],[-197,254],[31,191],[-114,-21],[-228,-216],[-180,3],[184,295],[299,61],[49,91],[-190,213],[-27,224],[-154,26],[-61,-128],[-97,213],[264,6],[206,92],[-8,104],[-295,83],[-3,155],[116,205],[154,-6],[-42,-107],[83,-53],[49,260],[113,-191],[288,16],[-45,98],[-185,49],[191,36],[31,456],[315,208],[-225,106],[53,179],[147,84],[-47,104],[-271,106],[53,108],[-170,188],[-162,-92],[-30,-175],[-156,-120],[-209,173],[-133,235],[-150,-33],[31,130],[204,-61],[63,197],[-198,117],[-38,138],[-193,33],[-35,188],[-263,219],[-220,41],[-162,205],[-150,-61],[-289,227],[-11,99],[111,25],[25,207],[-337,247],[-146,-105],[-51,-145],[-82,209],[-267,-108],[-109,-86],[19,-81],[-154,52],[-86,-77],[-131,228],[-202,15],[-108,-76],[-232,69],[-130,-156],[-111,26],[-62,-150],[-167,30],[-59,186],[-139,53],[44,205],[-200,284],[300,144],[-57,94],[-151,27],[101,76],[-147,160],[172,528],[8,144],[-98,106],[75,110]],[[31111,73536],[0,457],[562,43],[54,128]],[[42777,67480],[144,-147],[1285,-306]],[[48587,65366],[446,147]],[[49555,64630],[390,-104],[219,-175],[309,-102],[-389,-313],[-249,31],[-223,180]],[[48992,64036],[-290,19],[-57,-173],[844,-421]],[[52613,61308],[230,-2],[319,-120],[296,-262]],[[53404,60825],[-129,7],[-382,173],[72,-306]],[[53167,60081],[139,-278],[-218,-303],[-676,52],[-82,-48],[154,-304],[-2,-486]],[[52009,58559],[-224,140],[-306,48],[-125,-147],[-157,48],[-152,190],[-183,-147],[-226,-22],[-105,194],[-103,11],[-151,-138]],[[46803,57178],[-98,-138],[-102,-164]],[[23793,62669],[16,-274],[481,-170]],[[24290,62225],[233,-208],[-12,-122],[-473,-72],[-109,-78],[0,-122],[266,-145],[163,-491],[-12,-94],[-334,-122],[-49,-105],[429,-464],[164,-363],[147,-43],[-3,-97],[-264,-101],[-44,-273],[431,-608],[-53,-150],[-296,-155],[-49,-125],[113,-152],[36,-381],[253,-120]],[[24827,57634],[-119,-310],[421,-304]],[[15407,54605],[-125,-75],[-249,223],[-190,-123],[-108,127],[27,167]],[[14501,54921],[-52,318],[-254,-47]],[[12201,57026],[-20,255],[-293,108],[-98,-72],[-131,64]],[[10768,57320],[15,168],[-97,108],[102,116],[-301,88],[-194,495],[-337,186],[-128,-42],[-176,142],[62,248],[198,48],[54,130],[-72,448],[44,288],[206,166],[10,298],[-502,-299],[-85,-160],[-172,222],[-40,-205],[-136,74],[-276,-118],[59,-319],[-398,100],[-187,224],[-411,183],[-537,-119],[-401,46],[-309,383],[-875,433],[97,462],[191,136],[112,238],[-151,546],[184,539],[-233,586],[147,224],[-330,307],[19,252],[172,338],[377,119],[150,143],[158,235],[-12,111],[344,-67],[101,-121],[213,17],[17,-166],[191,86],[4,83],[248,-153],[146,53],[31,-113],[238,148],[129,296],[69,-121],[209,-25],[146,157],[391,-215],[300,58],[187,-171],[109,133],[215,-136],[160,-6],[-3,205],[133,-13],[83,90],[87,-140],[453,198],[74,-195],[288,-115],[-24,-65],[-164,-15],[80,6],[159,-237],[-26,-136],[-84,124],[-154,-258],[282,12],[-25,-216],[308,-49],[116,49],[0,-288],[84,92],[154,-55],[218,96],[70,-67],[170,9],[207,230],[-192,481],[126,89],[28,256],[110,-5],[119,-157],[229,42],[61,-151],[169,-43],[350,-715],[141,-486],[208,-288],[399,27],[328,-83],[229,67],[54,-74],[231,116],[163,-136],[316,70],[-158,123],[-131,357],[-112,-18],[-260,514],[120,144],[-53,248],[184,90],[75,466],[-506,822],[-2,219],[449,813],[-444,525],[-376,241],[-20,213],[-260,222],[-15,147],[-192,91],[-86,150],[-508,162],[188,373],[-82,-29],[-109,130],[32,160],[-180,44],[12,-81],[-93,-63],[-312,42],[-319,-139],[-98,208],[-223,78],[-203,-50],[-116,241],[-421,16],[-39,-153],[-301,-115],[-244,38],[-82,127],[-200,48],[75,324],[-227,154],[70,139],[-24,278],[36,84],[288,-31],[88,429],[297,133],[24,105],[-234,227],[-198,56],[339,433],[-175,142],[65,194],[-182,387],[256,246],[64,185],[-28,258],[193,176],[144,-323],[144,219],[333,46],[-14,217],[99,262],[98,66],[602,-273],[334,373],[497,-25],[455,-161],[186,161],[642,-288],[195,-794],[-7,-525],[81,-89],[316,-85]],[[21566,67422],[270,-301]],[[21965,67079],[117,-246],[181,-103]],[[23298,64927],[247,-196]],[[23545,64731],[27,-372]],[[23572,64359],[-221,-116],[75,-212]],[[23426,64031],[154,-22],[15,-238],[-120,-58],[206,-92],[85,-302],[-93,-155],[41,-229],[283,-141],[-204,-125]],[[16980,84844],[-18,78],[-49,-99]],[[16826,84750],[-87,32],[90,-75],[-198,-138],[99,47],[-27,-144]],[[26864,87384],[-126,427]],[[29851,74091],[-942,-497]],[[28909,73594],[-485,97],[-281,-196],[-262,72],[-66,-438],[-95,-158],[54,-1295],[-147,47],[-88,186],[-339,333],[-238,-150],[-460,82],[-512,-19],[-355,199],[-460,650],[-695,361],[-221,-170],[-270,-509],[-322,-220],[-79,-501],[-286,-123]],[[23302,71842],[-690,45],[-95,-321]],[[22517,71566],[49,-114],[243,-138],[-108,-357],[90,-96],[1,-150],[-59,87],[-85,-10],[-33,-145],[230,-86],[18,-397],[208,29],[-12,-164],[-214,-133],[149,-85],[41,-185],[101,-65],[-154,-98],[-24,-109],[126,-133],[165,-10],[-280,-241],[-8,-163],[174,-217],[-226,-99],[113,-387],[-130,-274],[-116,-55],[97,-207],[-146,-261],[144,-161],[-187,-303],[61,-114],[49,102],[115,-8]],[[22909,66819],[-25,-97],[64,-21],[18,-288],[-229,-26]],[[22737,66387],[158,-127],[138,100],[-144,-329],[231,-451],[118,-69],[-151,-98],[195,-135]],[[23282,65278],[-151,-133],[167,-218]],[[23298,64927],[-383,72],[-152,135],[-110,363],[-165,100],[98,279],[-273,353],[-32,225],[102,44],[-120,232]],[[22263,66730],[-167,86],[-131,263]],[[21965,67079],[-129,42]],[[21836,67121],[-60,132],[-210,169]],[[21566,67422],[-414,167],[-148,-64],[-252,113],[-234,-8],[-95,160],[-67,-114],[-223,42],[-70,164],[69,-17],[-98,108],[65,160],[-323,357],[-24,132],[-157,-32],[-85,61],[-10,83],[127,74],[-34,47],[-180,78],[-92,6],[-29,-78],[-85,35],[-452,349],[-318,399],[-371,318],[-208,155],[-58,-34],[-383,175],[5,77],[-137,16],[-43,225],[64,179],[-331,302],[110,125],[-192,111],[-5,182],[-185,50],[-494,351],[-403,92],[-82,143],[-209,-110]],[[15515,72001],[-344,111],[-71,221],[25,367],[-123,300],[40,203],[-97,269],[-657,310],[-83,133],[-346,199],[-473,189],[-414,434],[-29,155],[65,123],[-178,366],[-438,255],[-229,-318],[-236,-123],[-185,7],[-525,445],[-123,381],[447,683],[110,341],[224,221],[-79,650],[87,335],[136,83],[-15,97],[140,121],[186,717],[-1059,14],[-197,-131],[-294,42],[-167,-140],[-288,22],[-228,-148],[-275,45],[-151,-83],[-337,2],[-193,274],[-645,415],[-265,460],[-354,409],[-92,-2],[23,364],[-259,115],[50,130],[-95,182],[60,111],[-47,63],[119,121],[-23,167],[-152,194],[170,406],[-186,161],[198,-48],[-30,78],[215,138],[-22,117],[140,140],[-149,192],[103,110],[-108,158],[13,244],[116,30],[80,141],[17,135],[-81,106],[48,171],[-115,111],[166,188],[-153,93],[298,40],[-135,249],[-10,232],[237,-3],[-205,247],[253,10],[44,379],[-133,117],[90,278],[254,43],[367,242]],[[26920,88237],[-184,-466],[128,-387]],[[26864,87384],[-642,-843],[-1074,0],[-231,221],[-283,113],[-83,-122],[-320,6],[-486,-227],[-103,-96],[-31,-241],[-462,-424],[-879,266],[-205,-703],[-461,-735],[-898,-136],[-183,-155],[-219,-6],[-45,-190],[130,-340],[-809,-130],[-822,104],[-982,382],[-108,-24],[-56,102],[-323,108],[-239,-20],[-347,178]],[[16703,84472],[43,108],[-89,-25],[-14,66],[186,86],[-75,93],[72,-50]],[[16826,84750],[-13,94],[100,-21]],[[16913,84823],[29,96],[38,-75]],[[16980,84844],[85,11],[71,191],[-82,139],[86,47],[-18,169],[125,71],[-75,67],[60,17],[-39,88],[111,3],[40,117],[-153,-6],[-95,259],[-109,-18],[-153,185],[121,75],[41,204],[107,-8],[-167,205],[106,137],[8,-10]],[[17050,86787],[63,-72],[49,42],[-125,33]],[[17037,86790],[-106,30],[-34,304],[152,113],[-54,42],[-197,-83],[118,174],[-98,86],[64,55],[-103,-13],[-117,160],[-114,3],[1,89],[-116,-47],[-131,66],[-155,-53],[-179,42],[-252,-164],[-116,-242],[-806,-10],[-132,-166],[-320,-57],[-121,-192],[-198,18],[-299,-131],[-641,241],[-321,-406],[-2103,-221],[-1358,13],[-178,-105],[-180,71]],[[8943,86407],[-542,-306],[-229,254],[-423,-124],[-126,75],[-18,224],[165,-86],[53,46],[77,377],[-207,78],[91,77],[-51,34],[-298,-126],[-149,200],[-17,133],[203,115],[-32,73],[-220,53],[-3,85],[273,-52],[259,163],[193,-25],[94,86],[-67,277],[-351,-126],[-128,69],[-31,117],[469,453],[34,551],[205,146],[728,140],[665,311],[156,7],[-45,693],[380,227],[-13,351],[282,-196],[533,-113],[257,97],[68,163],[144,17],[235,423],[325,92],[317,-47],[31,154],[121,-24],[148,80],[121,245],[228,97],[32,102],[126,-87],[122,234],[-35,120],[180,148],[48,167],[288,52],[64,180],[80,-47],[250,174],[-44,125],[-276,6],[361,210],[-59,298],[135,84],[288,-67],[157,63],[-26,321],[-216,131],[-8,88],[232,110],[69,145],[362,47],[217,172],[25,110],[321,116],[467,528],[573,-479],[623,-217],[153,18],[176,401],[323,258],[869,-69],[10,-135],[148,-39],[34,-214],[100,-105],[-205,-140],[72,-108],[-80,-62],[74,-96],[-31,-106],[111,-68],[42,-227],[89,-3],[185,-352],[-193,-127],[196,-58],[129,169],[102,-194],[583,-71],[172,-134],[78,-522],[-80,-210],[-214,-169],[-266,71],[253,-370],[85,-13],[41,76],[144,-141],[432,-74],[465,296],[545,147],[206,-92],[1954,-139],[515,-567],[433,-99],[103,-251],[-141,-285],[21,-98],[85,-69],[110,26],[355,-230],[316,28],[346,149],[280,252],[232,653],[-329,215],[-290,514],[477,354],[144,332],[198,4],[111,185],[-23,108],[184,113],[92,252],[167,96],[240,-60],[74,60],[236,-170],[258,87],[274,-132],[141,17],[4,94],[100,-55],[74,121],[229,23],[211,199],[-39,157],[131,202],[164,27],[255,-118],[85,-183],[144,-88],[408,-36],[229,-134],[120,34],[206,-216],[310,-91],[294,-20],[158,186],[319,183],[11,-206],[110,-22],[-21,-144],[137,-165]],[[42269,85592],[23,-449],[-339,-58],[-252,-273],[-164,64]],[[41012,85523],[-202,-280],[-55,-717]],[[37366,75992],[-431,6],[-66,-402],[68,-138],[-64,-176],[-581,-639],[-885,-327],[-460,-521],[-54,-174],[113,-90],[-10,-122],[-119,-3],[-291,248],[-64,391],[-249,188],[-66,235],[-257,285],[17,219],[-87,143],[-709,-43],[498,-1086],[-758,-51],[-339,212],[-302,-75],[-342,225],[-201,-133]],[[31727,74164],[-39,-120],[-308,-69],[-269,18],[38,159],[-329,172]],[[30820,74324],[-287,-166],[-152,62]],[[30381,74220],[-530,-129]],[[29851,74091],[145,153],[117,313],[201,2504],[-188,143],[-336,-41],[-142,86],[49,387],[93,160],[-576,435],[324,262],[146,1375],[-25,570],[223,50],[471,426],[-311,165],[-239,333],[62,249],[221,216],[-286,320],[83,448],[-36,194],[231,219],[-36,302],[197,68],[142,158],[-277,138],[302,684],[-485,345],[272,1459],[-264,389],[-39,185],[-1457,883],[-246,67],[16,-194],[-88,-34],[-1377,303]],[[26738,87811],[182,426]],[[26920,88237],[308,86],[262,389],[36,207],[-94,70],[-3,171],[80,171],[244,120],[170,403],[104,109],[208,27],[95,249],[114,-39],[239,174],[367,28],[2,97],[137,-30],[100,-122],[124,139],[202,-83],[258,63],[533,-564],[244,2],[399,95],[437,282],[1148,436],[422,241],[-208,399],[84,695],[-375,8],[-156,86],[-41,191],[-86,15],[54,131],[-100,42],[121,143],[-118,150],[141,83],[-36,165],[60,50],[-37,78],[-80,-25],[11,72],[-159,-14],[23,202]],[[32154,93429],[-260,497],[152,100],[-108,296],[121,48],[-173,182],[309,226],[113,385],[-250,70],[36,169],[-256,11],[-203,206],[-119,-13],[85,288],[-174,75],[149,281],[-134,354],[85,114],[151,-74],[108,68],[-139,244],[49,75],[-49,191],[119,307],[-234,149],[146,258],[-18,171],[398,177],[-187,69],[74,251],[176,128],[-37,97],[435,-14],[128,-238],[28,-273],[227,-231],[421,-39],[339,-246],[174,-251],[519,-202],[1357,-14],[365,318],[34,130],[-85,241],[233,321],[-411,141],[-113,453],[28,314],[443,141],[1086,-360],[1007,979],[835,-315],[-95,-211],[-179,-141],[63,-304],[-136,-221],[26,-171],[265,-9],[64,-131],[247,-159],[198,5],[12,-102],[-179,-130],[-357,-14],[-113,-135],[35,-244],[260,11],[-142,-247],[144,26],[-7,-106],[-280,-409],[-312,-141],[-99,-271],[76,-135],[190,-43],[224,184],[278,-217],[-46,-151],[69,-78],[486,-25],[128,-136],[26,-74],[-190,-37],[-217,-182],[-18,-298],[80,-191],[267,-100],[154,-233],[-90,-143],[-177,75],[-148,-28],[-11,-249],[-97,-120],[112,-179],[343,-216],[-168,1],[-359,-364],[31,-129],[202,-157],[-167,-294],[-66,-23],[-62,161],[-170,63],[-442,-206],[276,-283],[-26,-337],[197,-77],[213,27],[62,-114],[-143,-314],[-242,82]],[[39039,91805],[-200,-83],[28,-280],[350,-185],[-44,-196]],[[38959,90515],[-48,-483],[-186,61]],[[71201,80400],[310,-377],[563,-332],[-35,-666],[313,-192],[-123,-298]],[[72244,78314],[-386,-341],[131,-351]],[[72403,77309],[79,-163],[-115,-218]],[[76309,75444],[822,22],[-24,-119],[-364,-354]],[[78425,73015],[155,-213],[-70,-140]],[[78705,70014],[304,-710],[-49,-148],[-147,-49],[-130,28],[-37,154],[-105,73],[-309,-62],[-41,-121]],[[77483,68393],[89,-296],[218,-89],[-48,-83],[-332,62],[-279,-156],[-417,-44],[-187,-207],[-39,-481],[-255,-253]],[[75820,66864],[-201,251],[-289,-71]],[[75281,67120],[-483,173],[-257,-200]],[[71902,67251],[-162,-36],[-673,591]],[[60407,72347],[121,146],[28,91],[-97,106],[90,232]],[[60667,73387],[216,954],[-178,403],[-110,-38],[30,-85]],[[54048,78704],[-354,112],[-239,-19],[-121,-151],[-85,119],[244,207]],[[53776,79450],[162,114],[-70,280],[-233,66],[2,63],[267,155]],[[54146,80109],[34,93],[-10,94],[-176,39]],[[53697,80184],[-183,345],[65,120]],[[46292,94546],[-509,114],[-85,100],[360,277],[331,112],[283,-176],[589,47],[450,454],[403,55],[193,-123],[213,54],[367,-147],[285,88],[75,-69],[293,52],[274,128],[663,-495],[157,-16],[-7,-119],[158,8],[-18,-174],[198,-108],[67,-329],[70,-23],[-46,-74],[125,-81],[139,52],[52,-66],[105,-238],[-42,-93],[-81,29],[38,-76],[174,-136],[171,25],[74,-87],[-13,-207],[106,-72],[92,76],[102,-20],[49,-230],[136,-35],[70,-128],[170,11],[176,-116],[127,97],[108,-180],[146,-17],[175,346],[418,-229],[201,174],[90,-20],[89,94],[96,-43],[35,143],[-115,31],[218,90],[104,-160],[154,-39],[-18,75],[112,17],[114,-125],[259,139],[318,-3],[168,-124],[225,237],[63,-41],[-81,-169],[286,-160],[-61,-50],[-54,93],[2,-196],[252,87],[76,-98],[201,-16],[390,254],[29,124],[118,-146],[203,97],[-154,-387],[367,-145],[-357,-276],[21,-188],[211,-89],[-270,-517],[347,83],[290,213],[77,-199],[-28,-262],[-144,-189],[-142,-2],[-112,-108],[138,-45],[449,149],[134,-22],[-148,-658],[457,-85],[79,-181],[-192,-66],[-113,125],[-208,-26],[-83,-191],[67,-85],[360,-31],[141,67],[-26,-113],[-254,-199],[8,-94],[152,66],[174,-75],[187,257],[396,128],[-64,-285],[-190,-252],[157,-141],[216,44],[392,-346],[122,-223],[100,-429],[-114,-40],[-166,191],[-122,-177],[0,-158],[135,-126],[259,-51],[82,-213],[203,-104],[51,-113],[-365,-59],[-8,-384],[-185,-109],[22,-265],[524,-262],[144,-170],[110,255],[231,100],[467,-238],[894,-153],[117,-350],[325,8],[252,-238],[-128,-210],[21,-321],[120,-244],[-459,117],[-29,-169],[303,-97],[54,-180],[195,-105],[-8,-167],[68,-68],[187,31],[-69,162],[116,106],[411,-125],[577,-969],[265,-173],[434,154],[165,399],[388,-131],[221,314],[455,-468],[331,-33],[301,379],[-132,282],[19,190],[117,61],[486,12],[195,-322],[-44,-163],[-258,-321],[25,-520],[165,-274],[686,14],[668,191],[287,-255],[18,-353],[98,-241],[300,-235],[165,35],[54,379],[311,108],[164,-27],[747,-716]],[[47741,66387],[336,274],[371,-97],[134,-224]],[[48455,65809],[-123,-202],[324,-141],[120,125],[140,-110],[-129,-65],[-200,-50]],[[48587,65366],[-1308,70],[-3073,1591]],[[44206,67027],[-421,143],[-838,138],[-170,172]],[[42777,67480],[-491,982],[-573,878],[-248,218],[-59,171],[-196,-27],[-213,77],[-287,459],[-50,-24],[-5,105],[-192,169],[18,138],[-167,281],[-172,97],[-52,208],[-118,41],[-540,578],[-352,158],[-5,335],[-84,174],[-329,117],[-465,1286],[937,896],[399,241],[-150,174],[-703,421],[-88,387],[-156,-99],[-85,35],[17,-132],[-364,-39],[-28,-61],[-240,124],[-133,-68],[-237,212]],[[37366,75992],[135,307],[-26,89],[359,702],[-5,429],[193,369],[113,76],[-236,325],[31,386],[289,466],[1809,683],[249,766],[31,1806],[373,224],[-286,1202],[360,704]],[[40755,84526],[83,780],[174,217]],[[41012,85523],[399,-394],[126,-253]],[[41537,84876],[138,-62],[90,19],[188,252],[310,34],[59,75],[-53,398]],[[42269,85592],[-478,254],[-376,435],[-569,251],[-283,178],[-11,74],[-336,75],[-562,540],[-76,179],[284,648],[858,52],[72,86],[-1093,641],[-1557,153],[-261,389],[-280,-5],[-80,80],[89,119],[126,-66],[104,78],[13,179],[81,59],[-49,-141],[98,-181],[314,-132],[131,503],[-308,-41],[-41,85],[451,305],[57,130],[160,-156],[-22,-270]],[[38725,90093],[116,-73],[105,61],[13,434]],[[38959,90515],[-162,-18],[-94,133],[115,223],[355,208]],[[39173,91061],[43,224],[-349,157],[-46,191],[72,156],[146,16]],[[39039,91805],[85,235]],[[39124,92040],[200,-94],[80,119],[291,-224],[765,-298],[378,-32],[585,198],[476,-231],[817,-112],[411,494],[237,119],[-55,548],[321,-8],[72,89],[152,22],[373,-252],[233,71],[87,183],[-172,247],[0,116],[306,199],[-59,307],[159,677],[221,-58],[173,70],[102,127],[203,64],[196,346],[616,-181]],[[46292,94546],[-187,-381],[-630,-120],[-120,-124],[272,-374],[98,-431],[331,-367],[-111,-449],[168,-194],[-24,-470],[69,-232],[-71,-139],[95,-263],[685,-774],[-40,-284],[221,-302],[36,-216],[-134,-307],[33,-265],[77,-17],[-10,-174],[85,-119],[-159,-288],[82,-99],[-52,-93],[109,-98],[-67,-211],[92,8],[88,-97],[23,-552],[179,-260],[391,-139],[41,-125],[-98,-79],[-36,-234],[121,-124],[198,-25],[51,-328],[599,-238],[-85,-89],[82,-75],[-80,-309],[-226,-131],[14,-71],[-95,15],[9,-221],[189,39],[-4,-194],[63,-54],[102,85],[147,-5],[89,-347],[157,112],[434,-195],[24,122],[236,69],[36,-40],[-121,-98],[223,-251],[-5,196],[-123,78],[421,-37],[222,163],[87,-87],[-103,-17],[28,-51],[95,-4],[82,152],[258,-84],[451,296],[122,-257],[-67,-150],[254,-137],[-54,-58],[-244,10],[-28,-165],[228,58],[170,-72],[105,-152],[277,44],[160,-214],[368,-118],[-39,-260],[138,80],[147,-31],[156,-171],[-66,-249],[195,-38],[83,127],[117,-70],[-33,-318],[365,293],[2,-104],[-167,-117],[0,-139],[62,-68],[198,10],[16,-101],[-106,21],[-35,-82],[81,-108],[330,-3],[-95,-183],[226,-205],[-230,-141],[158,-121],[-150,-177],[77,-136],[-26,-331],[-154,-178],[-266,131]],[[53579,80649],[-54,-56],[172,-409]],[[53697,80184],[297,151]],[[53994,80335],[190,-60],[-38,-166]],[[54146,80109],[-242,19]],[[53904,80128],[-272,-166],[236,-118],[63,-305],[-155,-89]],[[53776,79450],[-244,28],[29,-301],[-158,-106],[90,-99]],[[53493,78972],[-248,-227],[102,-100],[75,145],[224,-51],[-185,-434]],[[53059,77848],[100,-195],[-138,-62]],[[52613,76996],[50,-224],[-289,-426],[100,-107],[-175,-402],[-154,-91]],[[48006,70111],[-630,-741],[-12,-263],[375,-189]],[[76422,64075],[32,252]],[[76607,64551],[-4,190],[-163,130],[-658,253],[-39,118],[44,250]],[[76429,67037],[141,629],[173,138],[356,17],[278,158],[388,-31],[7,88],[-220,86],[-69,271]],[[77483,68393],[136,133],[395,-5],[299,242],[28,131],[-150,285]],[[78191,69179],[90,161],[291,10],[174,-240],[253,99],[-39,279],[-255,526]],[[78705,70014],[-279,77],[-153,-55],[-131,149],[-7,125],[339,114],[5,94],[-500,426],[-180,418],[-533,241],[-189,456],[102,96],[342,-79],[332,290],[657,296]],[[78510,72662],[62,171],[-147,182]],[[78425,73015],[-329,156],[-405,55],[-407,330],[-410,109],[241,172],[-10,291],[113,193],[126,-2],[333,-349],[152,155],[-71,293],[43,188],[-67,67],[-293,22],[-107,-185],[-176,-83],[-226,17],[-94,113],[-95,436]],[[76743,74993],[382,380],[-21,111],[-795,-40]],[[76309,75444],[-365,520],[-519,12],[-244,-94],[-221,204],[-240,-58],[-144,80],[-189,269],[-258,55],[-226,258],[-424,-56],[-271,78],[-636,-510],[-524,368],[49,235],[270,123]],[[72367,76928],[116,185],[-80,196]],[[72403,77309],[-414,313]],[[71989,77622],[-128,318],[18,92],[365,282]],[[72244,78314],[-15,221]],[[72229,78535],[125,265],[-36,86],[-195,44],[-84,95],[48,636],[-737,523],[-149,216]],[[71201,80400],[102,439],[-44,121],[-456,346],[-253,380]],[[70550,81686],[-379,310],[117,35],[-12,100],[95,3],[329,559],[-69,216],[105,110],[-91,175],[212,113],[-16,111],[-100,27],[3,122],[163,-20],[-56,185],[106,28],[38,100],[-74,229],[202,112],[-231,-17],[-80,85],[201,222],[154,-37],[185,172],[863,153],[178,149],[274,465],[334,132],[212,380],[108,18],[546,-440],[730,-166],[396,438],[552,-92],[298,56],[56,110],[-97,145],[134,323],[166,106],[391,-37],[368,117],[249,362],[1022,-99],[203,80],[317,-130],[429,472],[1074,148],[598,-117],[246,63],[447,402],[227,2],[329,-318],[1775,-93],[291,68],[634,-254],[334,147],[341,-44],[186,-56],[239,-244],[233,-39],[352,-5],[257,78],[54,-56],[-77,-561],[696,-374],[132,250],[282,206],[208,286],[241,124],[312,484],[151,80],[-15,-885],[108,-725],[125,-16],[478,260],[877,-589],[49,-651],[526,-719],[160,-17],[156,158],[598,80],[555,-1372],[345,-453],[167,-675],[1772,-2001],[638,-505],[495,-181],[1223,1252],[-107,-861],[200,-429],[46,-417],[-102,-300],[-304,-188],[-62,-141],[-285,-121],[-56,-177],[129,-427],[177,-144],[418,-63],[296,-318],[41,-149],[-128,-197],[-425,-174],[-359,-340],[-115,-438],[-193,-299],[-512,-138],[-159,-111],[-18,-124],[141,-227],[85,-475],[-321,-503],[156,-250],[250,-157],[635,-23],[755,-169],[190,-126],[141,-1043],[565,-419],[-64,-700],[370,-613],[33,-183],[-487,-288],[23,-296]],[[89922,66711],[-352,-160],[-347,-196]],[[84350,46597],[-49,224],[-66,11]],[[84298,46702],[-84,-52],[-74,35],[-4,141]],[[84050,46683],[-129,198],[23,-199],[-293,48]],[[83594,46832],[-284,20],[-283,-172],[202,269],[-9,271],[287,348]],[[83099,48621],[-188,449],[-583,160]],[[82351,49980],[-152,528],[-338,174]],[[81639,50638],[-378,-262],[-153,-14],[-152,110]],[[79710,52138],[103,489],[-159,346],[-172,-136]],[[75617,56544],[-359,-256],[-90,69],[-72,255],[80,286],[732,455],[-60,140]],[[75422,58368],[-3,246],[285,133],[797,-77],[97,110],[-38,150]],[[76160,63328],[-541,33],[-145,373],[95,84],[326,-55],[396,152],[131,160]],[[76422,64075],[200,-77],[465,30],[596,-593],[626,-390],[-123,-823],[244,-106],[507,-680],[988,-180],[178,-124],[547,212],[224,526],[1148,-49],[149,-175],[-249,-749],[85,-391],[357,-356],[231,256],[927,413],[65,255],[321,-173],[684,164],[439,623],[907,157],[-57,174],[77,396],[244,385],[167,505],[524,700],[213,570],[1409,551],[708,1229]],[[89223,66355],[541,315],[158,41]],[[89922,66711],[540,-80],[319,263],[411,85],[310,272],[1262,-170],[2351,543],[2739,1654]],[[97854,69278],[192,-47],[468,56],[1485,-8750],[0,-374],[-1036,-860],[-755,119],[-292,-346],[-65,-435],[493,-744],[-102,-414],[-83,-67],[-839,-28],[-433,-152],[-120,-249],[-532,-509],[-386,-707],[-172,102],[-140,282],[-206,71],[-165,-1405],[-658,-647],[41,-249],[-348,-351],[-16,-211],[-1205,-2494],[-133,-1772],[-211,-572],[-435,-1998],[36,-862],[-69,-166],[316,-441],[-1158,-1501],[-131,-1093],[-689,-199]],[[8712,40046],[-129,41],[-14,-173]],[[8366,39755],[-270,-104],[95,-147]],[[8046,38843],[-76,-20],[67,-104],[105,226]],[[8358,38550],[-55,-65],[72,-27],[-28,-67],[-85,-60],[154,55],[-76,-146],[-69,-26]],[[5884,36251],[-116,-4],[237,-292]],[[2777,36087],[11,124],[159,-47],[106,159],[143,27],[-74,395],[300,119],[-72,142],[200,-84],[77,130],[-130,0],[-5,84],[189,44],[14,155],[82,17],[36,-105],[123,157],[-16,111],[-81,22],[74,107],[216,0],[-19,-109],[91,33],[-69,533],[297,113],[-20,197],[66,-66],[109,41],[-157,330],[179,88],[154,366],[-87,40],[-61,-159],[-165,202],[60,88],[-96,2],[-76,174],[169,152],[-46,125],[234,-10],[95,148],[-175,225],[-47,528],[-82,138],[250,70],[4,57],[75,-71],[267,238],[91,-28],[-19,186],[182,107],[-145,131],[59,105],[-162,7],[-67,92],[76,107],[-79,57],[-146,466],[66,139],[-112,219],[171,528],[-28,191],[-77,36],[327,240],[31,227],[-60,37],[36,218],[-93,42],[-99,-56],[-73,116],[-151,14],[-16,99],[-49,-49],[-130,177],[-178,-30],[-125,110],[49,49],[-95,186],[-91,0],[-17,94],[-355,211],[183,267],[10,167],[-145,64],[-28,204],[-159,127],[10,89],[-354,445],[36,142],[-75,112],[-26,422],[57,271],[-79,321],[-222,282],[144,340],[-87,301],[36,147],[-237,471],[3,323],[-236,99],[-216,-122],[-273,256],[1244,1278],[77,-50],[3,-192],[179,-49],[-43,-377],[580,-16],[122,34],[169,240],[318,77],[70,-299],[611,-252],[884,-616],[198,244],[345,174],[110,260],[-160,490],[150,216],[85,323],[325,172],[121,160],[-126,152],[524,750],[253,669],[-6,335],[132,188],[-312,403],[111,187],[-285,-26],[-1,192],[-135,270],[31,304],[207,200],[232,714],[179,223],[39,380],[157,158],[49,198],[211,61],[-6,322],[105,196],[181,124],[212,-127],[432,-64],[-25,135],[254,83],[198,-170],[-90,-167],[98,-31],[17,-93],[216,80],[357,-166],[29,150]],[[10768,57320],[169,69],[11,-102],[122,-86],[165,61],[169,-155],[255,113],[0,161]],[[11659,57381],[485,-83],[57,-272]],[[12201,57026],[123,-83],[-53,-133],[154,-191],[-80,-71],[-7,-192],[51,-63],[62,99],[154,-102],[162,16],[153,-246],[176,43],[63,-104],[-81,-339],[71,50],[178,-65],[236,-364],[136,-23],[133,130],[363,-196]],[[14195,55192],[226,64],[69,-75],[-56,-125],[67,-135]],[[14501,54921],[261,3]],[[14762,54924],[32,-257],[117,-34],[152,114],[254,-222],[90,80]],[[15407,54605],[204,-69],[64,106],[197,39],[-38,162],[134,160],[202,-38],[78,105],[90,-221],[193,-34],[246,114],[15,114],[134,-211],[85,119],[111,-17],[154,249],[400,-18],[-30,170],[156,173],[-159,187],[152,123],[154,-18],[13,64],[-280,232],[120,513],[-38,320],[90,80],[51,244],[-62,97],[113,136],[-18,180],[-211,231],[26,127],[92,6],[181,227],[79,277],[213,316],[-9,198],[235,291],[253,121],[352,45],[143,-446],[466,-124],[888,-568],[183,-18],[223,-213],[97,29],[309,-118],[146,-291],[231,-157],[232,-330],[43,-365],[78,-21],[43,-180],[2004,16],[473,139],[414,-1],[7,163]],[[25129,57020],[100,-55],[-145,-498],[122,-246],[-53,-296]],[[25153,55925],[-59,-103],[-391,-215],[-44,-352],[-279,-99],[-9,-99],[50,-214],[359,-38],[219,-120]],[[24999,54685],[-72,-979],[46,-1035],[80,-113]],[[10384,41759],[-199,-266],[-203,-471]],[[9948,40865],[-102,-36],[-22,-114],[-167,53]],[[9339,40369],[-143,-10],[-85,-62],[85,61],[40,-99]],[[25867,34933],[13,-256],[-399,38]],[[23320,31034],[-251,943],[-1031,1021]],[[9830,40795],[118,70]],[[9948,40865],[-88,74],[122,83]],[[9982,41022],[48,233],[354,504]],[[10384,41759],[335,179],[354,360],[11,186],[467,87],[136,205],[620,-147],[1137,-729],[273,50],[769,476],[295,26],[303,-166],[354,-633],[524,-143],[244,18],[60,123],[61,-55],[116,60],[34,-85],[74,83],[120,-17],[-4,69],[-119,17],[36,163],[249,168],[-95,130],[52,91],[393,-96],[531,55],[119,462],[-293,327],[769,616],[-57,125],[136,69],[-38,114],[151,-81],[64,78],[-118,121],[-51,256],[-152,22],[67,157],[-196,199],[-27,385],[-62,79],[-87,-66],[-155,53],[-23,355],[-103,47],[308,201],[11,482],[-118,171],[184,132],[-58,288],[179,526],[344,337],[342,175],[309,13],[103,136],[253,99],[237,208],[198,25],[144,305],[439,124],[60,132],[623,62],[144,196],[72,-27],[170,121],[-59,338],[-123,190],[77,125],[-60,111],[144,215],[32,233],[528,598],[32,361],[190,70],[63,163],[358,-39],[390,72],[661,1008],[752,-230],[466,85]],[[25053,52558],[54,-277],[-134,-365]],[[26234,50495],[154,19],[101,-110],[25,-293]],[[24827,44228],[-49,-105],[516,-549]],[[25130,40586],[148,-358],[286,-204]],[[20034,19636],[-61,188],[-195,60],[-85,-44],[15,178],[-153,132],[-116,380],[-116,82],[25,261],[-205,22],[-69,694],[-155,273],[253,242],[-68,256],[-133,-46],[-39,254],[190,312],[4,277],[141,11],[-23,70],[-149,-36],[-145,122],[-64,182],[-102,-77],[-219,86],[-151,-773],[-132,-13],[-272,121],[-98,222],[-262,46],[157,130],[-72,163],[-130,28],[-157,-169],[-147,3],[20,-129],[-110,-108],[-239,519],[-200,22],[115,90],[172,-84],[63,37],[-453,417],[-242,9],[-95,-148],[-74,131],[-111,-22],[-41,185],[-431,19],[-152,181],[-170,-78],[60,342],[-83,266],[-162,-121],[-72,-210],[-163,-45],[194,-326],[-169,-156],[-488,324],[-214,232],[-122,50],[-78,-57],[-165,243],[-213,102],[-15,349],[-301,49],[-154,112],[6,249],[144,60],[2,91],[-116,70],[41,130],[288,108],[15,102],[-462,301],[-31,75],[177,204],[-194,316],[-127,-17],[-35,-126],[-301,201],[-103,-146],[23,-84],[-244,-93],[88,234],[-155,36],[65,170],[-34,357],[72,102],[-36,285],[283,144],[-114,144],[68,188],[-118,43],[-3,75],[354,42],[-537,583],[-613,397],[-180,271],[31,145],[-150,-5],[-49,-171],[-90,316],[-176,-184],[-307,294],[-138,-230],[-93,9],[-161,210],[-81,-92],[-37,112],[-199,-67],[-117,337],[-103,28],[-602,-128],[-154,-137],[-193,52],[-203,-130],[-215,102],[-190,-237],[-170,14],[-314,-175],[-516,27],[-223,-79],[-32,143],[-199,83],[-34,127],[-174,127],[-62,-65],[-108,11],[-5,79],[-167,-66],[-376,290],[-118,-80],[-128,70],[-95,-69],[-295,41],[-58,82],[281,98],[-44,94],[-179,-1],[-34,192],[-245,33],[-95,-80],[-125,191],[-409,165],[-64,111],[-87,-144],[-231,-64],[-52,-80],[-165,103],[-10,-103],[-197,-21],[-41,-145],[-149,69],[-47,145],[-221,141],[123,-8],[375,182],[-148,194],[5,212],[-167,233],[8,135],[-57,12],[-38,-117],[-64,66],[279,242],[-652,411],[-111,441],[-378,43],[154,-473],[-257,-220],[-58,-283],[-116,-52],[-226,55],[-260,191],[-284,531],[-332,227],[-345,63],[-336,-36],[-131,108],[105,293],[385,-27],[47,222],[198,210],[-203,54],[111,227],[202,-61],[74,-102],[148,86],[89,199],[-123,493],[131,41],[97,-118],[-23,-130],[129,36],[113,-65],[72,166],[-29,152],[172,59],[22,-110],[100,-4],[69,50],[-77,131],[85,123],[117,-32],[55,119],[143,-76],[24,94],[210,31],[-12,305],[128,79],[113,-124],[105,141]],[[2777,36087],[1863,-1192],[190,42],[103,223],[198,22],[79,-116],[93,252],[172,77],[47,126],[141,-86],[185,3],[64,118],[-72,153],[80,107],[-132,-44],[-20,69],[237,114]],[[6005,35955],[-63,140],[-185,123],[127,33]],[[5884,36251],[117,-141],[68,47],[-37,115],[240,-18],[0,137],[128,-29],[-105,55],[-23,119],[-167,82],[30,92],[196,56],[-42,149],[119,-42],[22,247],[278,-53],[60,-128],[-127,-108],[126,-77],[206,55],[61,128],[250,47],[-116,46],[110,42],[31,116],[-87,51],[-15,140],[89,114],[-95,171],[109,41],[104,-77],[81,72],[-81,94],[180,186],[155,-91],[69,170],[126,0],[-31,140],[136,-75],[91,190],[131,-100]],[[8271,38214],[145,134],[-141,-34],[83,236]],[[8358,38550],[-232,102],[98,63],[0,145],[-82,85]],[[8142,38945],[-77,-219],[-96,75],[77,42]],[[8046,38843],[-45,182],[207,160],[106,-90],[51,74],[-146,66],[7,200],[50,-113],[138,88],[-223,94]],[[8191,39504],[-87,165],[262,86]],[[8366,39755],[92,-104],[79,14],[-72,121],[104,128]],[[8569,39914],[22,181],[121,-49]],[[8712,40046],[-77,47],[52,36],[69,-56],[-2,-155],[110,161],[246,56],[-77,93],[203,31]],[[9236,40259],[-41,91],[-84,-53],[61,59],[167,13]],[[9339,40369],[152,148],[54,-40],[-70,122],[51,120],[101,-84],[30,133]],[[9657,40768],[145,-58],[28,85]],[[9830,40795],[498,-298],[247,2],[226,-151],[111,216],[390,-109],[128,-207],[247,19],[758,-1297],[3456,-96],[-75,-104],[124,32],[151,-178],[85,42],[89,-64],[81,-446],[112,108],[83,-43],[40,-186],[180,110],[136,-90],[-277,-607],[13,-174],[75,-14],[38,-212],[227,57],[-37,-64],[136,-342],[-113,-36],[24,-81],[339,-140],[-132,-260],[2562,-1192],[1356,-920],[764,-1006],[166,-66]],[[22038,32998],[964,-953],[326,-1040],[-26,-464]],[[42626,21198],[-634,-758],[-268,169]],[[40882,22056],[-289,55],[-1151,-58],[-343,-69]],[[35435,30278],[300,102]],[[41768,33586],[126,355]],[[52273,35904],[-111,-558],[232,-285]],[[53417,35078],[509,-208],[97,-174],[-149,-205],[61,-304],[-379,-255]],[[53730,32092],[170,-383],[141,-227],[329,-139],[265,64],[254,182],[596,48],[229,-319]],[[55004,29081],[-665,558]],[[51752,14449],[-350,66],[-72,1021]],[[46338,18729],[-308,-285],[-400,-119]],[[44403,18460],[-366,75],[-114,-124],[-261,-87]],[[43361,18319],[-93,-215],[-164,-106],[-123,252],[-260,27]],[[42276,19879],[91,125],[-41,88],[-62,-49],[-82,76],[-41,139]],[[42086,20205],[-159,164],[699,829]],[[42626,21198],[-10,437],[709,444],[387,-33],[-17,93],[285,380],[-46,445],[295,357],[29,224],[156,13],[640,441],[198,54],[744,573],[-50,1049],[318,882],[-57,1422],[77,247],[524,603],[733,-299],[229,30],[100,-125],[1109,34],[196,-216],[-11,-122],[213,-83],[443,185],[213,-168],[372,-88],[163,69],[189,276],[275,-20],[334,191],[288,-38],[2685,1184]],[[54339,29639],[892,-711]],[[58822,25262],[47,-923],[72,-263]],[[60012,22721],[-1418,-3868]],[[49612,64147],[193,-169],[279,-42],[391,343],[-920,351]],[[49555,64630],[-548,338],[-166,224],[56,122],[245,81],[-109,118]],[[49033,65513],[-117,-32],[-173,112],[-87,-127],[-311,111],[110,232]],[[48455,65809],[-77,56],[29,129],[-109,258],[80,47],[113,-45],[91,86]],[[48582,66340],[-158,244],[-379,67],[-304,-264]],[[47741,66387],[-308,355],[61,182],[-180,344],[309,13],[33,169],[-62,67],[124,74],[-43,183],[105,39],[-39,71],[110,172],[-423,154],[-33,101],[632,135],[-487,223],[199,249]],[[47739,68918],[-327,134],[-80,215],[674,844]],[[48006,70111],[1048,78],[190,115],[13,147],[146,197],[360,-20],[789,103],[282,-122],[157,45],[218,-189],[404,225],[5,127],[-174,130],[-325,49],[-218,279],[64,61],[465,-202],[88,366],[-359,158],[118,439],[-32,153],[91,13],[228,-212],[159,243],[-95,165],[-216,6],[37,86],[221,60],[473,-192],[40,220],[-251,322],[-285,205],[-543,162],[-236,373],[177,170],[0,223],[336,-50],[276,191],[-116,360],[368,347],[-165,185],[293,221],[-175,240],[216,44],[-283,164],[105,70],[245,-120]],[[52145,75746],[139,72],[18,122],[118,93],[54,230],[-106,56],[288,431],[31,136],[-74,110]],[[52613,76996],[213,139],[-219,318],[270,-67],[100,53],[44,152]],[[53021,77591],[147,75],[-109,182]],[[53059,77848],[232,100],[-172,102],[143,42],[29,125],[170,88]],[[53461,78305],[179,495],[408,-96]],[[54048,78704],[232,129],[657,72],[68,86],[328,75],[185,-19],[154,279],[111,-55],[133,-362],[31,-675],[213,-89],[314,5],[180,-202],[319,-94],[873,84],[292,127],[273,-183],[80,16],[131,-426],[220,-364],[-51,-931],[242,-38],[314,-340],[-109,-440],[290,-75],[81,-138],[115,-8],[31,-199],[108,-106],[228,-28],[75,-86],[206,9],[120,-113],[133,6]],[[60625,74621],[14,113],[136,-75],[98,-459],[-214,-637],[8,-176]],[[60667,73387],[-121,-120],[-59,-262],[62,-83]],[[60549,72922],[-90,-243],[98,-112],[-150,-220]],[[60407,72347],[-25,-194],[-164,-66],[-298,-429],[-132,18],[-31,130],[-139,-85],[93,-301],[6289,-84],[181,141],[126,-166],[244,-107],[362,99],[264,-324],[33,-223],[509,177],[483,-269],[219,-310],[223,247],[75,-61],[238,-445],[239,-263],[-123,-230],[127,-116],[-55,-130],[172,-512],[309,-526],[105,-5],[196,213],[226,-42],[136,55],[120,151],[155,-100],[146,96],[79,-126],[-43,-103],[164,-166],[-97,-102],[64,-92],[165,-16],[25,-275]],[[71067,67806],[606,-470],[52,-115],[177,30]],[[71902,67251],[-52,69],[137,74],[-42,92],[129,20],[-41,105],[72,52],[421,-268],[36,-221],[139,201],[111,23],[418,-277],[247,-9],[33,169],[488,-58],[39,-85],[41,93],[-66,109],[59,52],[236,-211],[143,26],[91,-114]],[[74541,67093],[246,202],[494,-175]],[[75281,67120],[49,-76]],[[75330,67044],[257,82],[233,-262]],[[75820,66864],[413,-18]],[[76233,66846],[196,191]],[[76429,67037],[563,-940],[-642,-454],[-361,-38],[-202,-113]],[[75787,65492],[-42,-283],[68,-100],[726,-295],[68,-263]],[[76607,64551],[-153,-224]],[[76454,64327],[-38,-310],[-98,-83],[-456,-177],[-293,61],[-106,-116],[183,-358],[514,-16]],[[76160,63328],[94,-83],[-79,-235],[-182,-116],[-225,-26],[-69,-105],[506,-323],[-210,-680],[-131,-84],[-452,131],[-28,-47],[-646,47],[-156,-50],[-92,-178],[875,-918],[-90,-238],[-341,-320],[46,-278],[118,-91],[576,-17],[152,-259],[244,-155],[113,-191],[377,-182]],[[76560,58930],[34,-183],[-126,-77],[-663,80],[-290,-47],[-109,-117],[16,-218]],[[75422,58368],[-191,-338],[-37,-257]],[[67156,54190],[-408,73],[-139,111],[-233,-106]],[[53131,59536],[168,232],[-132,313]],[[53167,60081],[170,356],[-372,262]],[[52965,60699],[-90,239],[59,67],[246,-150],[224,-30]],[[53404,60825],[54,99]],[[53458,60924],[-106,114],[-375,226],[-364,44]],[[52613,61308],[-86,437],[-418,161],[-280,351],[-442,266],[-137,-6],[-164,145],[-195,-20],[-138,121],[-63,236],[-192,-89],[-542,67],[-467,484]],[[49489,63461],[-656,284],[-203,163],[41,130],[321,-2]],[[48992,64036],[65,138],[164,-36],[93,75],[298,-66]],[[66376,54268],[243,97],[-130,-258]],[[67159,51496],[-31,-468],[-460,-201]],[[65355,50454],[-40,-137],[-697,-184],[-143,-427]],[[59881,49014],[-149,-63],[-149,127],[-101,-2],[-326,-352]],[[57856,47759],[-77,-250],[-123,-458]],[[56029,46646],[-107,-30],[-312,-318]],[[51842,45795],[18,257],[-80,114],[-445,-69]],[[50696,45682],[-335,298],[-380,-41],[-334,-147],[-230,-208]],[[48330,45291],[-208,453],[-694,357]],[[46890,48915],[70,124],[226,36],[88,101],[141,295],[-144,133],[648,487]],[[47919,50091],[-339,351],[0,136]],[[47580,50578],[546,246],[103,127],[-10,114]],[[48219,51065],[-570,284],[318,159],[74,148],[-490,153],[16,171],[316,177],[-168,409],[199,471],[-312,77],[-272,221],[-195,58],[-111,172]],[[47024,53565],[-215,50],[-291,210],[-193,426],[104,275]],[[46429,54526],[-55,326]],[[46374,54852],[209,406],[295,6],[262,-110]],[[47140,55154],[-185,502],[92,303],[131,116],[-54,304],[-246,472],[-275,25]],[[46603,56876],[200,302]],[[46803,57178],[-84,233],[33,431],[815,-251],[270,-570],[1800,-39],[-2,367],[208,50],[-108,161],[236,-13],[82,328],[232,100],[-6,221],[193,37],[-80,140],[23,203],[-138,160]],[[50277,58736],[33,61],[191,86],[108,-195],[154,-14],[282,164],[183,-207],[164,-28],[62,132],[187,3],[368,-179]],[[52009,58559],[87,215],[200,-105],[186,45]],[[52482,58714],[7,456],[-138,359],[780,7]],[[53131,59536],[1256,-1480],[422,-139],[329,-327],[15,-459],[362,8],[136,69],[875,-921],[179,164],[378,66],[876,-27],[552,346],[367,-11],[104,-117],[56,172],[591,-12],[513,-334],[2097,580],[183,136],[213,47],[997,106],[917,-235],[598,307],[44,-310],[-306,-166],[245,-423],[513,-413],[-156,-741],[-129,-219],[52,-238],[681,-321],[-127,-291],[280,37],[132,-122]],[[63418,35189],[-437,173],[-210,214],[-242,21],[-180,106],[-241,-42]],[[61040,35263],[-317,20],[-90,-183],[160,-1]],[[59678,37019],[-244,291],[94,168]],[[59415,37612],[183,2],[2,144],[142,222]],[[59641,38272],[152,140],[-3,113],[-171,-22],[-145,91],[216,310],[370,49],[648,-118],[264,27]],[[61635,39196],[710,153],[33,168]],[[64793,48633],[431,-208]],[[67815,37484],[550,-80],[27,-83]],[[68266,36917],[-413,329],[-118,-2],[-95,-131]],[[67663,36900],[-62,-96],[-138,-1],[-47,137],[-110,-3]],[[67228,36394],[-248,445],[-70,7],[-229,-280],[-172,211],[-192,234],[-317,-21],[-2,-83]],[[68266,36917],[8,124],[-152,266],[175,-41],[95,55]],[[68392,37321],[-22,72],[-229,89],[-326,2]],[[67815,37484],[-234,232],[76,197],[206,-197],[157,84],[242,-106],[90,87],[-73,191],[147,124],[-11,60],[-76,-43],[85,162],[231,-113],[138,144],[401,-299],[175,236],[364,-123],[294,358],[-100,116],[71,136],[295,296],[376,140],[580,-22],[175,59],[489,-144],[364,459],[360,158],[347,622],[477,105],[453,478]],[[74576,41340],[463,75],[647,-243]],[[77331,41094],[190,78],[280,-14],[146,-75]],[[78476,40660],[239,-63],[321,-374]],[[79379,40679],[213,-47],[-59,-187],[156,-296],[-22,-123],[-541,-580],[-190,-329],[532,-581],[-246,-324],[62,-340],[-59,-67],[-314,-28],[-285,-165],[164,-277]],[[79044,35813],[11,-547]],[[73043,29871],[-106,-132],[62,-120],[-103,-80]],[[67463,29542],[-339,-227],[-180,42]],[[65574,29666],[-832,-209],[-172,237],[-450,307],[23,224]],[[63735,30583],[-232,-45],[-62,182],[203,7],[-123,173]],[[63729,31545],[265,139],[-421,221],[59,75]],[[63447,32875],[-144,303],[-406,237],[-198,-119],[-219,5],[-97,73]],[[62971,34815],[-275,215],[34,134],[301,-116],[387,141]],[[63418,35189],[494,-440],[1574,-217],[212,-237],[488,-81],[352,600],[-68,115],[42,447],[-367,755],[-14,173],[332,116],[-465,487]],[[65998,36907],[8,96],[334,-6],[341,-431],[283,282],[264,-454]],[[67228,36394],[121,92],[-43,451]],[[67306,36937],[97,11],[47,-135],[141,-15],[72,102]],[[67663,36900],[-23,213]],[[67640,37113],[112,134],[101,-1],[134,-158],[279,-171]],[[83099,48621],[429,-495],[-21,-558]],[[83507,47568],[-301,-374],[13,-270],[-640,-675],[85,-189],[448,-205],[-183,-162],[-190,-48],[-491,78],[-203,-73],[6,-329]],[[81745,44151],[-62,181],[-431,149],[-106,-67],[-39,-279],[139,-476]],[[81229,43473],[123,-141],[419,-274]],[[82200,43058],[251,-13],[26,-106],[-272,-278]],[[81572,42417],[-320,-390],[-355,114],[-218,-32],[-229,-213]],[[78900,40752],[36,-457],[-166,268],[-294,97]],[[78476,40660],[-131,131],[-236,-14],[-162,306]],[[77947,41083],[-238,92],[-378,-81]],[[77331,41094],[-255,120],[-238,-67],[-142,-193],[-452,216],[-418,85],[-140,-83]],[[75686,41172],[-721,254],[-389,-86]],[[74576,41340],[-254,-276],[-408,-183]],[[73914,40881],[-242,570],[-116,80],[-239,1010],[-51,415],[108,227],[-1392,285],[-355,738],[-129,59],[-439,-182],[-470,426],[-938,99],[-143,-55],[-532,256],[-468,86],[-680,517],[-265,4],[-155,-145],[-210,79],[-494,389],[-108,452],[-282,275],[-182,455],[44,198],[-193,242],[-388,254],[-141,522],[-230,288]],[[65224,48425],[-210,76],[-367,400]],[[64443,49458],[134,367],[-10,266],[120,83],[186,-19],[89,107],[325,33],[68,159]],[[65355,50454],[135,27],[51,295],[383,347],[182,-86],[350,-5],[105,-181],[107,-24]],[[66668,50827],[473,229],[-36,304],[54,136]],[[67159,51496],[-87,312],[-115,108],[-104,949],[-364,739],[0,503]],[[66489,54107],[138,228],[529,-145]],[[67156,54190],[2488,438],[1302,967],[1357,1404],[234,121],[829,-88],[617,97],[493,205],[718,439]],[[75194,57773],[153,-130],[501,-150]],[[75848,57493],[60,-108],[-759,-519],[-53,-254],[95,-288],[108,-31],[318,251]],[[75617,56544],[553,42],[252,109],[177,-43],[48,-262],[-354,-359],[-44,-183],[-265,-119],[-451,-66],[-68,-141],[456,-126],[421,-2],[378,-193],[364,24],[221,-82],[273,-327],[22,-156],[-226,-472],[316,-265],[-282,-494],[436,62],[332,-150],[38,-71],[-104,-199],[123,-125],[390,55],[265,-116],[331,46],[263,-94]],[[79482,52837],[187,126],[146,-358],[-105,-467]],[[79710,52138],[33,-349],[404,-288],[175,18],[194,-98],[49,-282],[293,-354],[98,-313]],[[80956,50472],[138,-104],[221,24],[324,246]],[[81639,50638],[222,44]],[[81861,50682],[315,-151],[175,-551]],[[82351,49980],[-414,-316],[-36,-170],[231,-72],[196,-192]],[[82328,49230],[313,-85],[299,-106],[159,-418]],[[55426,31722],[116,-121],[-139,52],[-514,-64],[-417,-240],[-431,133],[-311,610]],[[53730,32092],[21,247],[92,117],[-152,466],[240,239],[108,364],[-394,159],[-89,248]],[[53556,33932],[718,496],[-2,650]],[[59600,37733],[-18,-135],[-167,14]],[[59415,37612],[113,-134]],[[59528,37478],[-87,-182],[237,-277]],[[59678,37019],[413,-104],[-25,-230],[-265,-80],[36,-149],[-124,8],[-41,-109],[96,-36],[-80,-115],[28,-158],[304,-99],[28,-241],[170,47],[18,-382],[-180,177],[-91,-89],[-4,-173],[156,-189],[622,-94],[54,96]],[[60793,35099],[-157,-15],[43,181],[361,-2]],[[61040,35263],[323,277],[388,0],[262,-83],[95,204]],[[62108,35661],[157,44],[506,-129],[137,-170],[393,-223],[-270,-135],[-275,123],[-62,-66],[75,-171],[202,-119]],[[62971,34815],[-118,-106],[186,-350],[-502,14],[128,-404],[-256,-272],[5,-116],[124,-91],[-155,-116]],[[62383,33374],[221,-84],[327,117],[470,-329],[46,-203]],[[63447,32875],[-82,-66],[-170,17],[-31,-230],[460,-78],[-206,-257],[121,-94],[303,-35],[127,-144],[-337,-8]],[[63632,31980],[-52,-97],[414,-178],[-265,-160]],[[63729,31545],[0,-177],[-112,-69],[69,-128],[195,-66],[-88,-129],[-272,-76]],[[63521,30900],[113,-185],[-202,-28],[89,-157],[214,53]],[[63735,30583],[141,-58],[267,-300]],[[64143,30225],[0,-176],[-59,-69],[-283,171],[-28,-131],[-373,-298],[-703,-205],[-556,11]],[[57273,30585],[-159,-22],[-260,-34]],[[57656,47051],[200,708]],[[57856,47759],[131,6],[105,118],[104,523],[429,388],[264,30],[273,-205],[-6,105]],[[59156,48724],[249,330],[178,24],[162,-129],[136,65]],[[59881,49014],[180,-97],[115,43],[-39,466],[758,891],[343,-210],[456,3],[163,233],[555,-105],[236,238],[318,-358],[226,-141],[105,-318],[122,-19],[69,99],[38,-75],[550,-152],[399,194]],[[64475,49706],[100,161],[-132,-409]],[[64443,49458],[140,-173],[64,-384]],[[64647,48901],[323,-357],[-177,89]],[[64793,48633],[-550,38],[-617,-325],[-459,-443],[103,-358],[12,-815],[127,-449],[262,-273],[185,-1115],[-219,-84],[-129,40],[-382,-513],[-37,-538],[-318,-1177],[11,-411],[-153,72],[-123,-134],[-459,-202],[285,-329],[166,-539],[-271,-946],[54,-88],[-41,-332],[138,-195]],[[62378,39517],[-93,-223],[-650,-98]],[[61635,39196],[-663,-334]],[[60972,38862],[-1222,80],[-293,-302],[-263,252],[31,87],[-161,345],[58,169],[-51,119],[-236,41]],[[55973,42312],[-38,235],[-596,3]],[[53733,42575],[-782,-177]],[[52166,42069],[-854,5],[-292,83],[-144,860],[247,442],[-36,87],[-741,406]],[[50100,43917],[-450,-311],[-272,23],[-360,226],[-714,988],[26,448]],[[48330,45291],[230,243],[857,50]],[[49417,45584],[336,269],[517,121],[120,-7],[306,-285]],[[50696,45682],[344,503],[295,-88]],[[51335,46097],[493,52],[14,-354]],[[51842,45795],[419,-48],[238,-597],[578,-58],[532,75],[306,-86],[167,-133],[747,977],[450,-152],[18,148],[263,26],[50,351]],[[55610,46298],[227,269],[192,79]],[[56029,46646],[573,-199],[520,354],[577,-99],[-43,349]],[[84142,22425],[105,-181],[439,-110],[165,150],[154,-355]],[[80015,13419],[-156,-19],[100,196],[-59,198],[-170,123],[23,405]],[[76580,18969],[-274,399],[118,271],[-75,116],[29,201],[58,-66]],[[76409,21090],[77,50],[-106,177]],[[76300,21282],[-182,212],[165,427]],[[74908,25783],[380,541],[-418,2302]],[[73223,29752],[-270,-38],[90,157]],[[73043,29871],[-196,142],[-69,292],[80,285],[-54,275],[80,216],[-193,328],[30,304],[219,559],[196,231],[357,199],[115,204],[44,667],[213,71],[251,227],[262,448],[239,86],[350,-50],[167,-99],[128,130],[440,66],[269,-230],[260,-32],[751,202],[290,-288],[539,-23],[254,291],[98,282],[471,208],[195,268],[226,136]],[[79055,35266],[13,150],[236,177]],[[84435,23216],[-106,-14],[-20,-329]],[[62444,20410],[-614,705]],[[59876,22352],[136,369]],[[60012,22721],[-1071,1355]],[[58941,24076],[-119,1186]],[[58822,25262],[-341,1044],[608,541],[57,203],[-175,382],[-365,397],[-770,156],[-240,125],[-482,7],[-802,202],[-532,686],[-449,-254],[-100,177]],[[55231,28928],[-227,153]],[[55004,29081],[407,1460],[303,777]],[[55714,31318],[-288,404]],[[55426,31722],[364,114],[208,-33],[-13,-394],[96,-176],[359,-217],[255,-378],[159,-109]],[[56854,30529],[419,56]],[[57273,30585],[195,-365],[909,39],[330,-116],[64,85],[61,-288],[371,-10],[212,-122],[60,-191],[1150,232],[243,-69],[258,-241],[553,-226],[131,17],[-5,88],[152,55],[-105,97],[41,110],[248,-152]],[[62141,29528],[335,-41],[599,107],[470,214],[279,349],[746,-463],[125,-224],[879,196]],[[65574,29666],[264,197],[666,-135],[440,-371]],[[66944,29357],[164,-42],[355,227]],[[67463,29542],[680,-38],[208,403],[466,-132],[149,69],[531,-50],[941,80],[403,-61],[154,-97],[16,169],[483,91],[706,-229],[44,-81],[652,-127]],[[72896,29539],[126,200],[201,13]],[[73223,29752],[450,326],[100,-26],[230,-596],[196,-46],[323,-549],[348,-235]],[[74870,28626],[421,-2332],[-383,-511]],[[74908,25783],[-521,-258],[-47,-224],[-118,-64],[-247,-397],[3,-161],[249,-131],[74,-314],[-140,-120],[-214,-595],[31,-116],[309,-227],[64,-264],[202,-145],[206,-55],[47,71],[167,-156],[256,-76],[132,114],[136,-125],[180,12],[436,-351],[170,-280]],[[76283,21921],[-100,-135],[23,-173],[-91,-85],[34,-119],[151,-127]],[[76300,21282],[80,35]],[[76380,21317],[108,-193],[-79,-34]],[[76409,21090],[-13,-300],[-118,-79],[89,-120],[-92,-106],[92,-11],[147,-460],[-47,-55],[67,-49],[-98,-20]],[[76436,19890],[-48,81],[-44,-123],[80,-196],[-116,-273],[70,-125]],[[71588,19364],[-495,105],[-226,-129]],[[71963,13442],[-6988,-686],[-2111,-343],[-3795,-255],[-96,-61],[-3694,-154],[-337,-83],[-798,-12],[-2552,-302],[-174,2975],[334,-72]],[[51752,14449],[617,-291],[54,-136],[-54,-196],[917,-1241],[151,4],[11,-243],[122,14],[1848,1220],[283,63],[1169,9],[-14,-265],[-236,-213],[655,-448],[732,420],[188,835],[311,351],[-54,250],[-157,245],[-2,197],[-316,157],[28,242],[-74,252],[128,185],[6,249],[141,157],[48,362],[181,222],[167,404],[32,338],[216,248],[-71,470],[53,155],[-130,340],[-108,48]],[[58594,18853],[1282,3499]],[[59876,22352],[153,-166],[469,-218],[233,-17],[54,-260],[334,113],[519,-39],[172,-253],[-46,-264],[66,-133]],[[61830,21115],[537,-552],[77,-153]],[[62444,20410],[-113,-248],[-452,-235],[-166,-310],[-257,-40],[10,-278],[251,-421],[661,110],[720,243],[177,-55],[593,106],[16,-534],[703,-318],[380,107],[568,341],[198,-247],[183,-91],[681,16],[251,81],[145,-53],[115,61],[123,-141],[401,3],[637,-221],[231,38]],[[68662,18225],[419,44],[532,-293]],[[41634,15614],[191,-393],[128,35]],[[42983,17757],[378,562]],[[43361,18319],[301,5]],[[43662,18324],[416,214],[325,-78]],[[44403,18460],[990,36],[106,-157],[131,-14]],[[45630,18325],[271,61],[437,343]],[[46338,18729],[177,519],[111,81],[183,-3],[-41,537],[1538,-1010],[614,186],[31,-364],[1572,-1946],[504,-78],[203,221],[881,-457],[-283,-231],[-197,-415],[-301,-233]],[[51330,15536],[262,-3990],[-6733,-1037],[-833,-279],[-206,-133],[-745,-168],[-85,-183],[-362,-67],[-138,-115],[-123,11],[-276,-142],[-663,-72],[-218,-290],[-611,-305],[-977,-364],[-231,-180],[-477,-113],[-224,-106],[-33,-86],[-840,-218]],[[36408,8421],[-215,271],[-283,202],[8,119],[61,63],[88,-61],[66,53],[142,-36]],[[36355,11027],[-237,1311]],[[36508,12592],[-117,283],[-145,53],[-287,347]],[[35736,13682],[-9,615],[75,440],[280,152],[52,207],[174,172],[20,121],[-135,1],[192,83]],[[33924,18574],[-157,168]],[[33770,19018],[246,274],[136,-94]],[[34769,19520],[198,-130],[64,-322]],[[37650,18108],[241,-105],[103,72]],[[38279,18930],[315,81],[312,188]],[[39304,19600],[18,-48],[120,-165]],[[30255,17104],[383,-464],[7,-604],[137,-329]],[[31894,15141],[150,-54],[77,-137],[560,135]],[[35139,15143],[131,150],[236,77],[265,-58]],[[35964,15334],[133,89],[231,-34],[-246,-500],[-254,-128],[-70,-126],[-22,-953]],[[35736,13682],[64,59],[266,-31],[-143,-83],[36,-352]],[[35959,13275],[516,-520],[33,-163]],[[36508,12592],[-143,-185],[-247,-69]],[[36118,12338],[-5,-119],[242,-1192]],[[36355,11027],[122,-153],[126,-11],[29,-278],[352,-317],[59,-215],[-79,-204],[120,-189],[-275,-335],[-175,-69],[-112,45],[-247,-269]],[[36275,9032],[-308,41],[-67,-166],[508,-486]],[[36408,8421],[170,-27],[454,143],[289,-117],[215,-389],[123,35],[-5,-148],[163,-219]],[[37817,7699],[-1141,-409],[-540,-58],[-283,-150],[-328,-44],[-283,-144],[-108,-185],[-810,-128],[-110,-74],[-811,-59],[-360,-119],[-350,-194],[-138,-243],[-271,-152],[-1219,-342],[-16,-159],[-408,-71],[-592,16],[-51,-80],[-2405,-359],[-59,-131],[64,-172],[-652,-320],[-372,-290],[-42,-158],[-373,-120],[-71,-174],[-345,-212],[-95,-289],[-374,-65],[-81,-105],[-1648,-131],[-448,-141],[-712,-399],[-364,-431],[-629,-114],[-247,-160],[-119,-185],[-480,-219],[-128,-146],[-684,-247],[-93,-155],[-1410,-381],[-496,53],[-254,-51],[-136,142],[-167,-5],[-293,312],[-33,158],[139,282],[346,274],[-319,149],[-139,175],[117,370],[120,106],[-66,203],[81,161],[-220,369],[31,137],[112,1],[-77,183],[59,140],[-262,333],[70,101],[192,25],[167,269],[-115,149],[-98,431],[-246,111],[100,174],[174,54],[-175,306],[219,91],[-89,404],[58,274],[-123,462],[97,241],[-302,89],[-247,221],[15,290],[180,125],[-167,290],[133,177],[-125,133],[44,191],[-181,161],[3,137],[106,139],[182,70],[252,-57],[92,228],[211,27],[105,-121],[242,38],[7,109],[-172,193],[-18,163],[70,100],[-183,180],[-249,96],[219,216],[79,272],[-218,213],[21,215],[125,205],[-93,121],[-61,318],[-151,92],[256,288],[250,85],[53,106],[201,110],[103,-71],[-26,-183],[87,-30],[183,218],[-54,74],[69,94],[180,64],[61,337],[75,-2],[110,307],[3,285],[-82,130],[46,218],[-75,-124],[26,171],[-121,89],[1,116],[118,194],[224,103],[-19,286],[-236,103],[80,200],[82,80],[170,-127],[166,187],[160,14],[157,150],[233,25],[-62,-224],[-122,-75],[128,-110],[-123,-223],[162,6],[215,383],[198,96],[-43,354],[149,122],[110,-36],[144,205],[-260,187],[34,426],[102,236],[-175,-53],[-71,-241],[-203,-38],[-357,320],[-96,311],[-318,398],[179,211],[85,-184],[217,-44],[76,228],[-128,264],[10,245],[65,115],[161,8],[108,286],[193,85],[-218,227],[259,-13],[118,105],[13,69],[-288,199],[83,208],[-50,310],[75,85],[304,-20],[-139,239],[94,257]],[[20034,19636],[1224,425],[3520,357]],[[26159,17832],[2018,-50],[896,19],[468,-492]],[[40882,22056],[87,-74],[-78,-152],[113,-119],[68,-36],[66,88],[367,-213],[0,-183],[-140,-82],[86,-192],[-76,-206],[116,-3],[10,127],[92,71],[-49,-52],[80,-23],[100,-398]],[[41724,20609],[108,-108],[147,-5],[-52,-127],[87,-110],[72,-54]],[[42086,20205],[55,53]],[[42141,20258],[50,-149],[163,-53],[-78,-177]],[[42276,19879],[14,-301],[-248,-50],[175,-55],[-43,-163],[80,-267],[220,-419],[106,-12],[141,-335]],[[42721,18277],[231,-13],[110,-102],[50,-225],[-129,-180]],[[42983,17757],[229,-268],[18,-172],[128,-33],[69,-122],[-123,-119],[-26,-246],[-69,66],[-93,-51],[-38,-242],[-215,-191],[-50,-253],[88,-200],[-335,-395],[-331,-75],[-177,55],[-105,-255]],[[41953,15256],[-162,-10],[-157,368]],[[41634,15614],[134,196],[-254,733],[-258,1555],[-374,93],[-116,-129],[-290,-1],[-178,-135],[-455,260],[123,323],[-72,100],[27,178],[-152,166],[-232,104],[-135,189],[40,141]],[[39442,19387],[-138,213]],[[39304,19600],[-319,-202],[-79,-199]],[[38906,19199],[-416,-236],[-211,-33]],[[38279,18930],[-54,-281],[-167,-140],[-64,-434]],[[37994,18075],[-72,-72],[-272,105]],[[37650,18108],[5,-85],[-267,-117],[5,-94],[-98,4],[0,-147],[-281,-169],[-174,20],[34,188],[-67,82],[-221,84],[-177,190],[-291,105],[-151,293],[-100,37],[-68,-59],[-300,297],[-264,121],[-62,138],[-142,72]],[[35031,19068],[-93,358],[-169,94]],[[34769,19520],[-362,-244],[-64,33],[-191,-111]],[[34152,19198],[-158,83],[-224,-263]],[[33770,19018],[66,-127],[-69,-149]],[[33767,18742],[42,-71],[115,-97]],[[33924,18574],[255,19],[393,-313],[519,-207],[135,-149],[34,-350],[328,-166],[116,32],[365,-429],[314,-123],[113,-160],[-113,-371],[-173,-39],[232,-337],[-116,-119],[59,-389]],[[36385,15473],[-421,-139]],[[35964,15334],[-65,77],[-128,-99]],[[35771,15312],[-393,19],[-239,-188]],[[35139,15143],[-97,61],[-59,-171],[-262,-59],[-119,-140],[-259,-45],[-303,11],[-95,91],[-232,-104],[-251,227],[-160,-159],[-278,-100],[-41,-109],[-444,-97],[77,188],[-44,72],[160,185],[-51,91]],[[32681,15085],[-504,-152],[-283,208]],[[31894,15141],[-13,118],[-125,-19],[-140,88],[-23,-75],[-112,191],[-324,-38],[7,100],[-382,201]],[[30782,15707],[-188,672],[56,231],[-123,223],[-225,147],[-47,124]],[[30255,17104],[-714,205]],[[29541,17309],[-449,485],[-2933,38]],[[26159,17832],[-1381,2586]],[[24778,20418],[31,5995],[-687,3464],[-428,216],[-392,448]],[[23302,30541],[18,493]],[[23320,31034],[170,502],[1084,-256],[327,152],[-90,295],[-404,174],[-662,532],[41,160],[-60,67],[129,237],[36,689],[282,816],[907,53],[401,260]],[[25481,34715],[142,1],[503,-159],[65,-79]],[[26321,34452],[149,-55],[299,-540],[189,-559],[-423,-359],[-373,25],[-76,-97],[37,-146]],[[34240,29819],[1195,459]],[[35435,30278],[223,-855],[13,-998],[216,-639],[783,-1600],[1136,-832],[79,-420],[-86,-697],[253,-325],[-66,-130],[44,-252],[536,-259],[121,-348],[-77,-277],[283,-327],[21,-263],[-60,-72],[173,-121],[72,121]],[[39099,21984],[875,98],[908,-26]],[[79956,14689],[-53,-207],[-150,-160]],[[79753,14322],[-25,-354],[215,-272],[13,-172],[-97,-124],[52,-11],[104,30]],[[80015,13419],[176,235],[257,-88],[187,44],[282,468],[198,-6],[306,-141],[306,241],[-110,216],[-36,446],[-250,105],[67,494],[-36,404],[-521,802],[1241,751],[135,874],[353,326],[650,-74],[677,451],[42,152],[375,321],[277,57],[167,-104],[173,497],[272,89],[634,504],[429,79],[-84,222],[-357,61],[-105,317],[-271,64],[-117,264],[-168,157],[47,118],[-206,164]],[[85005,21929],[-321,590],[82,88]],[[88725,29061],[-10,287],[170,247],[324,3],[875,-1519],[424,-2623],[164,-124],[142,-8],[41,-332],[-59,-244],[591,-1399],[-113,-2228],[1197,105],[-203,-1169],[288,-67],[229,-280],[133,-10],[88,133],[567,96],[180,168],[64,-52],[14,128],[167,46],[38,89],[48,-53],[-53,-63],[174,-22],[41,-92],[465,-262],[142,30],[-31,-52],[106,-95],[215,145],[16,-72],[159,-6],[79,-128],[-25,-163],[239,-64],[-67,-1009],[264,-1547],[252,-469],[163,-300],[94,-3],[-100,-149],[-20,-586],[-208,103],[-286,-58],[-138,201],[-91,-13],[-117,-156],[107,-166],[-115,-64],[98,-22],[90,-187],[-11,-208],[-43,-157],[-201,8],[-65,-128],[52,-130],[221,-157],[-156,-25],[4,-55],[42,38],[64,-116],[93,25],[35,-86],[111,16],[69,-102],[-34,-47],[-95,70],[103,-133],[-128,58],[-56,-150],[174,-47],[-95,-58],[74,-177],[-130,-17],[120,-257],[149,30],[-30,-109],[144,-302],[-81,-147],[98,-94],[67,27],[-100,-88],[41,-100],[133,20],[67,-185],[60,11],[-70,-158],[-72,64],[6,-95],[-95,9],[-36,-213],[-239,21],[-77,-256],[-109,138],[-246,44],[-65,-58],[-17,139],[-90,-181],[-262,86],[-8,-80],[-72,0],[-29,105],[-69,-119],[-252,255],[-121,-103],[44,-90],[-171,-10],[-234,220],[-216,80],[-142,-70],[-77,55],[-23,-118],[-79,44],[-149,-86],[18,-174],[-98,-102],[-208,229],[-257,-191],[-380,-19],[-966,388],[-899,94],[-548,-222],[59,-423],[-5151,963],[-4879,611],[-1449,291],[-982,348]],[[88725,29061],[-238,-227],[-113,-348],[133,-460],[-485,-929],[30,-601],[-146,-226],[61,-299],[-130,-196],[-93,36],[-116,-303],[-111,42],[-7,-105],[-249,-69],[93,-194],[122,-28],[-63,-85],[87,-61],[100,55],[-36,-68],[156,-186],[-555,-324],[-182,114],[-103,-28],[-7,-113],[-218,-106],[-165,-212],[-26,-228],[-211,-196],[-343,-575],[-340,-329],[-44,-197],[-179,-235],[-149,-28],[-159,152],[-273,103]],[[84766,22607],[-90,-125],[142,-199],[-96,-138],[-390,50],[-190,230]],[[84142,22425],[167,448]],[[84309,22873],[-5,301],[131,42]],[[84435,23216],[39,141],[-207,221],[-122,321],[333,763],[165,81],[-111,411],[167,117],[367,55],[91,277],[-59,185],[200,113],[-182,369],[-193,188],[118,255],[-139,41],[-120,-58],[-52,90],[70,244],[431,136],[-8,93],[-210,170],[-62,234],[59,108],[191,-27],[5,226],[-204,194],[-121,374],[-151,202],[-380,-25],[-21,-117],[154,-179],[-269,-23],[-28,330],[-357,316],[-32,226],[124,189],[110,13],[260,-141],[120,28],[9,122],[-378,227],[-98,572],[-501,446],[74,339],[-215,47],[10,307],[-386,278],[-138,-90],[62,-130],[-106,-88],[-465,310],[-270,-165],[-298,381],[-77,446],[-388,253],[-121,167],[-22,221],[180,341],[-185,729],[-224,225],[31,368],[-442,229],[13,243],[-72,92],[211,283],[-63,271],[-285,29],[-359,-292],[-131,-9],[-137,99],[-336,-15]],[[79304,35593],[-216,-186],[-44,406]],[[79044,35813],[-429,493],[560,395],[-148,333],[-262,187],[25,114]],[[78790,37335],[-156,302],[277,140],[347,58],[-31,396],[246,275],[-71,152],[-435,393],[-23,115],[182,280],[504,497],[64,186],[-154,291],[23,249],[-184,10]],[[79379,40679],[-343,-456]],[[79036,40223],[-130,153],[-6,376]],[[78900,40752],[399,559],[424,119],[274,-81],[8,305],[445,242]],[[80450,41896],[192,192],[255,53],[377,-98],[298,374]],[[81572,42417],[-105,296],[548,-204],[118,-233],[144,102],[-72,283]],[[82205,42661],[279,331],[-74,81],[-210,-15]],[[82200,43058],[-85,-93],[-344,93]],[[81771,43058],[-448,299],[-94,116]],[[81229,43473],[17,186]],[[81246,43659],[-134,395],[34,360],[137,66],[364,-126],[98,-203]],[[81745,44151],[311,75],[303,819],[-308,276]],[[82051,45321],[-14,313],[173,89],[529,-78],[337,172],[28,85],[-463,177],[-62,170],[415,466],[53,-36],[134,133],[92,-35],[13,75],[308,-20]],[[83594,46832],[57,-102]],[[83651,46730],[270,-53],[20,202],[109,-196]],[[84050,46683],[86,143]],[[84136,46826],[54,-177],[108,53]],[[84298,46702],[-63,130]],[[84235,46832],[84,-23],[31,-212]],[[84350,46597],[188,47],[2,-185],[149,-51],[250,-843],[413,92],[223,-375],[329,198],[157,5],[65,150],[113,43],[405,-85],[165,35],[82,435],[-82,168],[-186,105],[-23,134],[489,89],[465,-72],[154,-126],[43,-1224],[93,-183],[285,-199],[18,-488],[350,-242],[218,30],[249,-250],[439,-252],[293,-419],[810,-869]],[[90506,42265],[-221,-100],[-2369,-3626],[-21,-695],[391,-329],[-111,-146],[129,-274],[-111,-48],[-56,-281],[-182,-108],[31,-175],[-134,-196],[15,-163],[-144,7],[-251,-610],[-18,-155],[436,-271],[-46,-938],[1056,-3724],[13,-669],[-170,-343],[-18,-360]],[[52291,36738],[111,-585],[-129,-249]],[[52273,35904],[-1516,-26],[-3941,-2352],[-3103,431],[-1092,55],[-727,-71]],[[41894,33941],[-1089,772]],[[40737,51214],[52,233],[637,4]],[[41426,51451],[-100,158],[342,426],[-152,197],[33,144],[59,114],[73,-3],[15,-92],[82,17],[-41,85],[254,438],[6,223],[303,-61],[17,119],[309,0],[116,-177],[272,-66],[380,-335],[1043,50],[33,-279],[334,-74],[578,365],[77,444]],[[45459,53144],[348,-30],[30,-97],[157,-68]],[[45994,52949],[-41,-678],[64,-213],[147,-227],[175,-53],[-95,-194],[-163,-97],[326,-871],[91,-497],[154,-148],[290,-82]],[[46942,49889],[473,-418],[-198,-373],[-228,-42],[-99,-141]],[[46890,48915],[381,-446],[-164,-503],[-26,-445],[115,-197],[452,-418],[-20,-126],[-244,-302],[44,-377]],[[47428,46101],[506,-223],[249,-208],[147,-379]],[[48330,45291],[-8,-497],[724,-969],[499,-232],[247,75],[308,249]],[[50100,43917],[246,35]],[[50346,43952],[781,-448],[-249,-467],[100,-824],[581,-208],[70,-91],[-157,-122]],[[51055,38417],[455,-268],[293,-283],[69,-404]],[[40805,34713],[1097,-806],[-134,-321]],[[41768,33586],[36,-564],[-123,-55],[45,-157],[-82,-139],[-189,-67],[-299,-503],[-56,-437],[-219,-249],[55,-229],[-216,-325],[17,-160],[-534,50],[-432,235],[-388,-185],[-410,149],[-1580,120],[-386,-545],[-1272,-145]],[[35735,30380],[-1495,-561]],[[34240,29819],[-1365,930],[-1510,-1174],[-994,-2],[-1326,-445],[-774,1410],[-369,1378],[-489,404],[-1066,431],[-224,-30]],[[26123,32721],[-2,215],[414,3],[375,291],[59,141],[-319,744],[-131,117],[10,98],[-208,122]],[[26321,34452],[-159,-110],[29,136]],[[26191,34478],[-352,290],[28,165]],[[25867,34933],[534,587],[74,463],[-151,289],[301,595],[-177,100],[25,459],[-229,473],[93,181],[-218,671],[-640,51],[-278,135],[-77,627],[358,228],[82,232]],[[25564,40024],[-380,318],[-54,244]],[[25130,40586],[123,478],[-10,199],[-109,133],[142,423],[54,535],[167,368],[-300,295],[-24,366],[121,191]],[[25294,43574],[-445,403],[-72,160],[50,91]],[[24827,44228],[339,114],[-145,499],[150,918],[-93,298],[178,477],[-379,547],[3,110],[337,86],[111,180],[161,66],[-7,324],[451,70],[283,293],[5,232],[-252,213],[-153,262],[35,399],[-182,152],[-113,232],[400,260],[458,-15],[100,166]],[[26514,50111],[-62,370],[-218,14]],[[26234,50495],[-308,467],[-321,-53],[-365,335],[-72,410],[-195,262]],[[24973,51916],[64,189]],[[25037,52105],[241,61]],[[25278,52166],[592,1684],[5993,26]],[[31863,53876],[263,-76],[641,19],[135,-115],[1970,-802],[1565,539],[652,102],[1383,12]],[[38472,53555],[115,-67]],[[38587,53488],[134,-401],[406,-382],[-65,-667],[517,-165],[280,-252],[413,-66],[484,-198]],[[40756,51357],[-19,-143]],[[40737,51214],[-3573,-1790],[72,-849],[-75,-152],[-506,-363],[-303,-77],[-376,-665],[78,-138],[-110,-234],[28,-116],[-126,-115],[-111,-455],[-239,-178],[72,-307],[-203,-890],[3605,155],[-111,566],[245,385],[1218,25],[48,-160],[417,-311],[-129,-224],[175,-216],[976,-475],[717,-205],[-240,-304],[-230,-523],[-2683,-1939],[-193,-1965],[553,-1139],[13,-1132],[1089,-1742],[-252,-83],[242,-177],[-20,-708]],[[71588,19364],[1963,-47],[303,-93],[1768,204],[756,-174]],[[76378,19254],[202,-285]],[[76580,18969],[-13,-157],[232,-9],[41,-127],[136,-9],[267,-458],[149,-67],[24,-246],[77,-62],[61,108],[78,-40],[133,90],[106,-209],[59,8],[5,-170],[110,7],[105,-369],[-131,-111],[59,-238],[95,-10],[-7,-155],[154,31],[-25,-83],[73,-15],[-87,-41],[57,-102],[-74,-14],[-185,-413],[56,-206],[522,-217],[324,3],[185,-365],[246,-171],[97,-271],[447,-192]],[[79956,14689],[-1084,-370],[-428,223],[-129,-188],[16,-301],[-109,-152],[-362,53],[-337,-324]],[[77523,13630],[-1854,373],[-332,-43],[-102,-151],[-1544,-91],[-1728,-276]],[[71963,13442],[-40,467],[-298,398],[-1344,650],[-236,-146],[-191,-262],[-159,339],[331,781],[-54,265],[59,227],[291,478],[324,79],[87,337],[-74,111],[-162,-12],[-173,174],[-207,354],[-265,260],[-239,34]],[[69613,17976],[-514,288],[-437,-39]],[[68662,18225],[-162,99]],[[68500,18324],[584,1010],[418,-215],[1365,221]],[[70867,19340],[136,99],[190,15],[395,-90]],[[53733,42575],[477,-152],[121,-123],[411,195],[93,155],[185,101],[126,-19],[193,-182]],[[55339,42550],[624,-19],[10,-219]],[[55973,42312],[-116,-158],[157,-2],[129,-106],[54,63],[166,-21],[85,-266],[430,-61],[-72,-146],[171,-310],[165,-102],[95,32],[144,-185],[208,-77],[385,-6],[363,-564],[-10,-139],[140,-301],[-61,-88],[269,-83],[160,-139]],[[58835,39653],[219,-21],[140,-740],[302,-262],[-8,-89],[274,-3],[32,-68],[-153,-198]],[[59641,38272],[88,3],[-48,-141],[61,-154]],[[59742,37980],[-142,-247]],[[59600,37733],[-629,-96],[-1765,-67],[-355,-254],[-128,11],[-486,-556],[-406,-197],[-1282,-1084],[-277,-412]],[[54272,35078],[38,-589],[-130,-175],[-198,-100],[-116,219],[157,263],[-133,207],[-473,175]],[[53417,35078],[-1023,-17]],[[52394,35061],[-205,194],[-11,373],[223,462],[-110,648]],[[52291,36738],[-419,724]],[[51872,37462],[-112,476],[-429,351],[-276,128]],[[51055,38417],[-102,707],[-388,136],[-167,264],[5,188],[-128,124],[56,183],[395,262],[63,910],[231,286],[67,267],[213,119],[172,-71]],[[51472,41792],[152,110],[-65,103],[-270,83],[877,-19]],[[52166,42069],[785,329]],[[52951,42398],[484,91],[298,86]]]}
